Workbook

Sheet Building
A1: Building | B1: Level | C1: Time (Computed) | D1: Build Buff | E1: Days | F1: Hours | G1: Minutes | H1: Seconds | I1: Gold | J1: Wood | K1: Stone | L1: Mana | M1: Specific Requirements | N1: Total sec | O1: Total sec pr
A2: Hall of Order | B2: 1 | C2: =trunc(O2/86400)&" days "&mod(trunc(O2/3600),24)&" hours "&mod(trunc(O2/60),60)&" minutes" -> 0 days 0 hours 0 minutes | N2: =H2+G2*60+F2*3600+E2*86400 -> 0 | O2: =ROUNDUP(N2*(D2+1),0) -> 0 | Q2: Ok
A3: Hall of Order | B3: 2 | C3: =trunc(O3/86400)&" days "&mod(trunc(O3/3600),24)&" hours "&mod(trunc(O3/60),60)&" minutes" -> 0 days 0 hours 0 minutes | D3: 0 | E3: 0 | F3: 0 | G3: 0 | H3: 2 | I3: 2500 | J3: 2500 | K3: 0 | L3: 0 | M3: / | N3: =H3+G3*60+F3*3600+E3*86400 -> 2 | O3: =ROUNDUP(N3*(D3+1),0) -> 2 | Q3: Need value
A4: Hall of Order | B4: 3 | C4: =trunc(O4/86400)&" days "&mod(trunc(O4/3600),24)&" hours "&mod(trunc(O4/60),60)&" minutes" -> 0 days 0 hours 5 minutes | D4: 0 | E4: 0 | F4: 0 | G4: 5 | H4: 0 | I4: 6500 | J4: 6500 | K4: 0 | L4: 0 | M4: / | N4: =H4+G4*60+F4*3600+E4*86400 -> 300 | O4: =ROUNDUP(N4*(D4+1),0) -> 300 | Q4: Do not touch
A5: Hall of Order | B5: 4 | C5: =trunc(O5/86400)&" days "&mod(trunc(O5/3600),24)&" hours "&mod(trunc(O5/60),60)&" minutes" -> 0 days 0 hours 20 minutes | D5: 0 | E5: 0 | F5: 0 | G5: 20 | H5: 0 | I5: 11800 | J5: 11800 | K5: 0 | L5: 0 | M5: Wall 3 | N5: =H5+G5*60+F5*3600+E5*86400 -> 1200 | O5: =ROUNDUP(N5*(D5+1),0) -> 1200
A6: Hall of Order | B6: 5 | C6: =trunc(O6/86400)&" days "&mod(trunc(O6/3600),24)&" hours "&mod(trunc(O6/60),60)&" minutes" -> 0 days 1 hours 0 minutes | D6: 0 | E6: 0 | F6: 1 | G6: 0 | H6: 0 | I6: 21300 | J6: 21300 | K6: 0 | L6: 0 | M6: Wall 4, Mint 4 | N6: =H6+G6*60+F6*3600+E6*86400 -> 3600 | O6: =ROUNDUP(N6*(D6+1),0) -> 3600
A7: Hall of Order | B7: 6 | C7: =trunc(O7/86400)&" days "&mod(trunc(O7/3600),24)&" hours "&mod(trunc(O7/60),60)&" minutes" -> 0 days 2 hours 0 minutes | D7: 0 | E7: 0 | F7: 2 | G7: 0 | H7: 0 | I7: 36300 | J7: 36300 | K7: 12000 | L7: 0 | M7: Wall 5, Scout Camp 5 | N7: =H7+G7*60+F7*3600+E7*86400 -> 7200 | O7: =ROUNDUP(N7*(D7+1),0) -> 7200 | Q7: Check your buff percentage by clicking on your city hall Then do the job <3
A8: Hall of Order | B8: 7 | C8: =trunc(O8/86400)&" days "&mod(trunc(O8/3600),24)&" hours "&mod(trunc(O8/60),60)&" minutes" -> 0 days 5 hours 0 minutes | D8: 0 | E8: 0 | F8: 5 | G8: 0 | H8: 0 | I8: 54400 | J8: 54400 | K8: 19200 | L8: 0 | M8: Wall 6, Infantry Camp 6 | N8: =H8+G8*60+F8*3600+E8*86400 -> 18000 | O8: =ROUNDUP(N8*(D8+1),0) -> 18000
A9: Hall of Order | B9: 8 | C9: =trunc(O9/86400)&" days "&mod(trunc(O9/3600),24)&" hours "&mod(trunc(O9/60),60)&" minutes" -> 0 days 10 hours 0 minutes | D9: 0 | E9: 0 | F9: 10 | G9: 0 | H9: 0 | I9: 81800 | J9: 81800 | K9: 30800 | L9: 0 | M9: Wall 7, Alliance Center 7 | N9: =H9+G9*60+F9*3600+E9*86400 -> 36000 | O9: =ROUNDUP(N9*(D9+1),0) -> 36000
A10: Hall of Order | B10: 9 | C10: =trunc(O10/86400)&" days "&mod(trunc(O10/3600),24)&" hours "&mod(trunc(O10/60),60)&" minutes" -> 0 days 15 hours 0 minutes | D10: 0 | E10: 0 | F10: 15 | G10: 0 | H10: 0 | I10: 122800 | J10: 122800 | K10: 49200 | M10: Wall 8, Lumber Mill 8 | N10: =H10+G10*60+F10*3600+E10*86400 -> 54000 | O10: =ROUNDUP(N10*(D10+1),0) -> 54000
A11: Hall of Order | B11: 10 | C11: =trunc(O11/86400)&" days "&mod(trunc(O11/3600),24)&" hours "&mod(trunc(O11/60),60)&" minutes" -> 0 days 22 hours 0 minutes | D11: 0 | E11: 0 | F11: 22 | G11: 0 | H11: 0 | I11: 184300 | J11: 184300 | K11: 78700 | N11: =H11+G11*60+F11*3600+E11*86400 -> 79200 | O11: =ROUNDUP(N11*(D11+1),0) -> 79200
A12: Hall of Order | B12: 11 | C12: =trunc(O12/86400)&" days "&mod(trunc(O12/3600),24)&" hours "&mod(trunc(O12/60),60)&" minutes" -> 1 days 6 hours 0 minutes | D12: 0 | E12: 1 | F12: 6 | G12: 0 | H12: 0 | I12: 277500 | J12: 277500 | K12: 120000 | N12: =H12+G12*60+F12*3600+E12*86400 -> 108000 | O12: =ROUNDUP(N12*(D12+1),0) -> 108000
A13: Hall of Order | B13: 12 | C13: =trunc(O13/86400)&" days "&mod(trunc(O13/3600),24)&" hours "&mod(trunc(O13/60),60)&" minutes" -> 1 days 16 hours 0 minutes | D13: 0 | E13: 1 | F13: 16 | G13: 0 | H13: 0 | I13: 417500 | J13: 417500 | K13: 180000 | N13: =H13+G13*60+F13*3600+E13*86400 -> 144000 | O13: =ROUNDUP(N13*(D13+1),0) -> 144000
A14: Hall of Order | B14: 13 | C14: =trunc(O14/86400)&" days "&mod(trunc(O14/3600),24)&" hours "&mod(trunc(O14/60),60)&" minutes" -> 2 days 2 hours 0 minutes | D14: 0 | E14: 2 | F14: 2 | G14: 0 | H14: 0 | I14: 627500 | J14: 627500 | K14: 270000 | N14: =H14+G14*60+F14*3600+E14*86400 -> 180000 | O14: =ROUNDUP(N14*(D14+1),0) -> 180000
A15: Hall of Order | B15: 14 | C15: =trunc(O15/86400)&" days "&mod(trunc(O15/3600),24)&" hours "&mod(trunc(O15/60),60)&" minutes" -> 2 days 12 hours 0 minutes | D15: 0 | E15: 2 | F15: 12 | G15: 0 | H15: 0 | I15: 942500 | J15: 942500 | K15: 405000 | N15: =H15+G15*60+F15*3600+E15*86400 -> 216000 | O15: =ROUNDUP(N15*(D15+1),0) -> 216000
A16: Hall of Order | B16: 15 | C16: =trunc(O16/86400)&" days "&mod(trunc(O16/3600),24)&" hours "&mod(trunc(O16/60),60)&" minutes" -> 2 days 22 hours 0 minutes | D16: 0 | E16: 2 | F16: 22 | G16: 0 | H16: 0 | I16: 1400000 | J16: 1400000 | K16: 607500 | N16: =H16+G16*60+F16*3600+E16*86400 -> 252000 | O16: =ROUNDUP(N16*(D16+1),0) -> 252000
A17: Hall of Order | B17: 16 | C17: =trunc(O17/86400)&" days "&mod(trunc(O17/3600),24)&" hours "&mod(trunc(O17/60),60)&" minutes" -> 4 days 0 hours 0 minutes | D17: 0 | E17: 4 | F17: 0 | G17: 0 | H17: 0 | I17: 2100000 | J17: 2100000 | K17: 912500 | N17: =H17+G17*60+F17*3600+E17*86400 -> 345600 | O17: =ROUNDUP(N17*(D17+1),0) -> 345600
A18: Hall of Order | B18: 17 | C18: =trunc(O18/86400)&" days "&mod(trunc(O18/3600),24)&" hours "&mod(trunc(O18/60),60)&" minutes" -> 4 days 20 hours 0 minutes | D18: 0 | E18: 4 | F18: 20 | G18: 0 | H18: 0 | I18: 3200000 | J18: 3200000 | K18: 1400000 | N18: =H18+G18*60+F18*3600+E18*86400 -> 417600 | O18: =ROUNDUP(N18*(D18+1),0) -> 417600
A19: Hall of Order | B19: 18 | C19: =trunc(O19/86400)&" days "&mod(trunc(O19/3600),24)&" hours "&mod(trunc(O19/60),60)&" minutes" -> 5 days 20 hours 0 minutes | D19: 0 | E19: 5 | F19: 20 | G19: 0 | H19: 0 | I19: 4800000 | J19: 4800000 | K19: 2100000 | N19: =H19+G19*60+F19*3600+E19*86400 -> 504000 | O19: =ROUNDUP(N19*(D19+1),0) -> 504000
A20: Hall of Order | B20: 19 | C20: =trunc(O20/86400)&" days "&mod(trunc(O20/3600),24)&" hours "&mod(trunc(O20/60),60)&" minutes" -> 7 days 0 hours 0 minutes | D20: 0 | E20: 7 | F20: 0 | G20: 0 | H20: 0 | I20: 7200000 | J20: 7200000 | K20: 3100000 | N20: =H20+G20*60+F20*3600+E20*86400 -> 604800 | O20: =ROUNDUP(N20*(D20+1),0) -> 604800
A21: Hall of Order | B21: 20 | C21: =trunc(O21/86400)&" days "&mod(trunc(O21/3600),24)&" hours "&mod(trunc(O21/60),60)&" minutes" -> 8 days 6 hours 0 minutes | D21: 0 | E21: 8 | F21: 6 | G21: 0 | H21: 0 | I21: 10800000 | J21: 10800000 | K21: 4700000 | N21: =H21+G21*60+F21*3600+E21*86400 -> 712800 | O21: =ROUNDUP(N21*(D21+1),0) -> 712800
A22: Hall of Order | B22: 21 | C22: =trunc(O22/86400)&" days "&mod(trunc(O22/3600),24)&" hours "&mod(trunc(O22/60),60)&" minutes" -> 11 days 2 hours 0 minutes | D22: 0 | E22: 11 | F22: 2 | G22: 0 | H22: 0 | I22: 16200000 | J22: 16200000 | K22: 7000000 | N22: =H22+G22*60+F22*3600+E22*86400 -> 957600 | O22: =ROUNDUP(N22*(D22+1),0) -> 957600
... A24: Hall of Order | B24: 23 | C24: =trunc(O24/86400)&" days "&mod(trunc(O24/3600),24)&" hours "&mod(trunc(O24/60),60)&" minutes" -> 23 days 23 hours 0 minutes | D24: 0.85 | E24: 12 | F24: 22 | G24: 48 | H24: 39 | I24: 36500000 | J24: 36500000 | K24: 15900000 | N24: =H24+G24*60+F24*3600+E24*86400 -> 1118919 | O24: =ROUNDUP(N24*(D24+1),0) -> 2070001
A25: Hall of Order | B25: 24 | C25: =trunc(O25/86400)&" days "&mod(trunc(O25/3600),24)&" hours "&mod(trunc(O25/60),60)&" minutes" -> 36 days 0 hours 0 minutes | D25: 0 | E25: 36 | F25: 0 | G25: 0 | H25: 0 | I25: 48100000 | J25: 48100000 | K25: 25500000 | L25: 3400000 | N25: =H25+G25*60+F25*3600+E25*86400 -> 3110400 | O25: =ROUNDUP(N25*(D25+1),0) -> 3110400
A26: Hall of Order | B26: 25 | C26: =trunc(O26/86400)&" days "&mod(trunc(O26/3600),24)&" hours "&mod(trunc(O26/60),60)&" minutes" -> 126 days 3 hours 46 minutes | D26: 0.71 | E26: 73 | F26: 18 | G26: 37 | H26: 50 | I26: 72200000 | J26: 72200000 | K26: 38200000 | L26: 5100000 | N26: =H26+G26*60+F26*3600+E26*86400 -> 6374270 | O26: =ROUNDUP(N26*(D26+1),0) -> 10900002
A27: Mint | B27: 1 | C27: =trunc(O27/86400)&" days "&mod(trunc(O27/3600),24)&" hours "&mod(trunc(O27/60),60)&" minutes" -> 0 days 0 hours 0 minutes | N27: =H27+G27*60+F27*3600+E27*86400 -> 0 | O27: =ROUNDUP(N27*(D27+1),0) -> 0
A28: Mint | B28: 2 | C28: =trunc(O28/86400)&" days "&mod(trunc(O28/3600),24)&" hours "&mod(trunc(O28/60),60)&" minutes" -> 0 days 0 hours 1 minutes | D28: 0.43 | H28: 42 | I28: 0 | M28: / | N28: =H28+G28*60+F28*3600+E28*86400 -> 42 | O28: =ROUNDUP(N28*(D28+1),0) -> 61
A29: Mint | B29: 3 | C29: =trunc(O29/86400)&" days "&mod(trunc(O29/3600),24)&" hours "&mod(trunc(O29/60),60)&" minutes" -> 0 days 0 hours 1 minutes | D29: 0.43 | H29: 56 | I29: 0 | M29: / | N29: =H29+G29*60+F29*3600+E29*86400 -> 56 | O29: =ROUNDUP(N29*(D29+1),0) -> 81
A30: Mint | B30: 4 | C30: =trunc(O30/86400)&" days "&mod(trunc(O30/3600),24)&" hours "&mod(trunc(O30/60),60)&" minutes" -> 1 days 6 hours 10 minutes | D30: 0.43 | F30: 21 | G30: 5 | H30: 50 | I30: 0 | M30: / | N30: =H30+G30*60+F30*3600+E30*86400 -> 75950 | O30: =ROUNDUP(N30*(D30+1),0) -> 108609
A31: Mint | B31: 5 | C31: =trunc(O31/86400)&" days "&mod(trunc(O31/3600),24)&" hours "&mod(trunc(O31/60),60)&" minutes" -> 1 days 9 hours 20 minutes | D31: 0.58 | F31: 21 | G31: 5 | H31: 50 | I31: 0 | M31: / | N31: =H31+G31*60+F31*3600+E31*86400 -> 75950 | O31: =ROUNDUP(N31*(D31+1),0) -> 120001
A32: Mint | B32: 6 | C32: =trunc(O32/86400)&" days "&mod(trunc(O32/3600),24)&" hours "&mod(trunc(O32/60),60)&" minutes" -> 0 days 0 hours 2 minutes | D32: 0.58 | G32: 1 | H32: 16 | I32: 0 | M32: / | N32: =H32+G32*60+F32*3600+E32*86400 -> 76 | O32: =ROUNDUP(N32*(D32+1),0) -> 121
A33: Mint | B33: 7 | C33: =trunc(O33/86400)&" days "&mod(trunc(O33/3600),24)&" hours "&mod(trunc(O33/60),60)&" minutes" -> 0 days 0 hours 0 minutes | I33: 0 | M33: / | N33: =H33+G33*60+F33*3600+E33*86400 -> 0 | O33: =ROUNDUP(N33*(D33+1),0) -> 0
A34: Mint | B34: 8 | C34: =trunc(O34/86400)&" days "&mod(trunc(O34/3600),24)&" hours "&mod(trunc(O34/60),60)&" minutes" -> 0 days 0 hours 0 minutes | I34: 0 | M34: / | N34: =H34+G34*60+F34*3600+E34*86400 -> 0 | O34: =ROUNDUP(N34*(D34+1),0) -> 0
A35: Mint | B35: 9 | C35: =trunc(O35/86400)&" days "&mod(trunc(O35/3600),24)&" hours "&mod(trunc(O35/60),60)&" minutes" -> 0 days 0 hours 0 minutes | I35: 0 | M35: / | N35: =H35+G35*60+F35*3600+E35*86400 -> 0 | O35: =ROUNDUP(N35*(D35+1),0) -> 0
A36: Mint | B36: 10 | C36: =trunc(O36/86400)&" days "&mod(trunc(O36/3600),24)&" hours "&mod(trunc(O36/60),60)&" minutes" -> 0 days 0 hours 0 minutes | I36: 0 | M36: / | N36: =H36+G36*60+F36*3600+E36*86400 -> 0 | O36: =ROUNDUP(N36*(D36+1),0) -> 0
A37: Mint | B37: 11 | C37: =trunc(O37/86400)&" days "&mod(trunc(O37/3600),24)&" hours "&mod(trunc(O37/60),60)&" minutes" -> 0 days 0 hours 0 minutes | I37: 0 | M37: / | N37: =H37+G37*60+F37*3600+E37*86400 -> 0 | O37: =ROUNDUP(N37*(D37+1),0) -> 0
A38: Mint | B38: 12 | C38: =trunc(O38/86400)&" days "&mod(trunc(O38/3600),24)&" hours "&mod(trunc(O38/60),60)&" minutes" -> 0 days 0 hours 0 minutes | I38: 0 | M38: / | N38: =H38+G38*60+F38*3600+E38*86400 -> 0 | O38: =ROUNDUP(N38*(D38+1),0) -> 0
A39: Mint | B39: 13 | C39: =trunc(O39/86400)&" days "&mod(trunc(O39/3600),24)&" hours "&mod(trunc(O39/60),60)&" minutes" -> 0 days 0 hours 0 minutes | I39: 0 | M39: / | N39: =H39+G39*60+F39*3600+E39*86400 -> 0 | O39: =ROUNDUP(N39*(D39+1),0) -> 0
A40: Mint | B40: 14 | C40: =trunc(O40/86400)&" days "&mod(trunc(O40/3600),24)&" hours "&mod(trunc(O40/60),60)&" minutes" -> 0 days 0 hours 0 minutes | I40: 0 | M40: / | N40: =H40+G40*60+F40*3600+E40*86400 -> 0 | O40: =ROUNDUP(N40*(D40+1),0) -> 0
A41: Mint | B41: 15 | C41: =trunc(O41/86400)&" days "&mod(trunc(O41/3600),24)&" hours "&mod(trunc(O41/60),60)&" minutes" -> 0 days 0 hours 0 minutes | I41: 0 | M41: / | N41: =H41+G41*60+F41*3600+E41*86400 -> 0 | O41: =ROUNDUP(N41*(D41+1),0) -> 0
A42: Mint | B42: 16 | C42: =trunc(O42/86400)&" days "&mod(trunc(O42/3600),24)&" hours "&mod(trunc(O42/60),60)&" minutes" -> 0 days 0 hours 0 minutes | I42: 0 | J42: 98000 | K42: 73500 | L42: 9000 | M42: / | N42: =H42+G42*60+F42*3600+E42*86400 -> 0 | O42: =ROUNDUP(N42*(D42+1),0) -> 0
A43: Mint | B43: 17 | C43: =trunc(O43/86400)&" days "&mod(trunc(O43/3600),24)&" hours "&mod(trunc(O43/60),60)&" minutes" -> 0 days 18 hours 3 minutes | D43: 0.56 | E43: 0 | F43: 11 | G43: 34 | H43: 27 | I43: 0 | J43: 147000 | K43: 111000 | L43: 14000 | M43: / | N43: =H43+G43*60+F43*3600+E43*86400 -> 41667 | O43: =ROUNDUP(N43*(D43+1),0) -> 65001
A44: Mint | B44: 18 | C44: =trunc(O44/86400)&" days "&mod(trunc(O44/3600),24)&" hours "&mod(trunc(O44/60),60)&" minutes" -> 0 days 0 hours 0 minutes | I44: 0 | J44: 235000 | K44: 176000 | L44: 22000 | M44: / | N44: =H44+G44*60+F44*3600+E44*86400 -> 0 | O44: =ROUNDUP(N44*(D44+1),0) -> 0
A45: Mint | B45: 19 | C45: =trunc(O45/86400)&" days "&mod(trunc(O45/3600),24)&" hours "&mod(trunc(O45/60),60)&" minutes" -> 0 days 0 hours 0 minutes | I45: 0 | M45: / | N45: =H45+G45*60+F45*3600+E45*86400 -> 0 | O45: =ROUNDUP(N45*(D45+1),0) -> 0
A46: Mint | B46: 20 | C46: =trunc(O46/86400)&" days "&mod(trunc(O46/3600),24)&" hours "&mod(trunc(O46/60),60)&" minutes" -> 0 days 0 hours 0 minutes | I46: 0 | M46: / | N46: =H46+G46*60+F46*3600+E46*86400 -> 0 | O46: =ROUNDUP(N46*(D46+1),0) -> 0
A47: Mint | B47: 21 | C47: =trunc(O47/86400)&" days "&mod(trunc(O47/3600),24)&" hours "&mod(trunc(O47/60),60)&" minutes" -> 0 days 0 hours 0 minutes | I47: 0 | M47: / | N47: =H47+G47*60+F47*3600+E47*86400 -> 0 | O47: =ROUNDUP(N47*(D47+1),0) -> 0
A48: Mint | B48: 22 | C48: =trunc(O48/86400)&" days "&mod(trunc(O48/3600),24)&" hours "&mod(trunc(O48/60),60)&" minutes" -> 0 days 0 hours 0 minutes | I48: 0 | M48: / | N48: =H48+G48*60+F48*3600+E48*86400 -> 0 | O48: =ROUNDUP(N48*(D48+1),0) -> 0
A49: Mint | B49: 23 | C49: =trunc(O49/86400)&" days "&mod(trunc(O49/3600),24)&" hours "&mod(trunc(O49/60),60)&" minutes" -> 3 days 5 hours 46 minutes | D49: 0.71 | E49: 1 | F49: 21 | G49: 29 | H49: 3 | I49: 0 | J49: 1900000 | K49: 1400000 | L49: 170000 | M49: / | N49: =H49+G49*60+F49*3600+E49*86400 -> 163743 | O49: =ROUNDUP(N49*(D49+1),0) -> 280001
A50: Mint | B50: 24 | C50: =trunc(O50/86400)&" days "&mod(trunc(O50/3600),24)&" hours "&mod(trunc(O50/60),60)&" minutes" -> 4 days 1 hours 13 minutes | D50: 0.7 | E50: 2 | F50: 9 | G50: 11 | H50: 23 | I50: 0 | J50: 3000000 | K50: 2200000 | L50: 270000 | M50: / | N50: =H50+G50*60+F50*3600+E50*86400 -> 205883 | O50: =ROUNDUP(N50*(D50+1),0) -> 350002
A51: Mint | B51: 25 | C51: =trunc(O51/86400)&" days "&mod(trunc(O51/3600),24)&" hours "&mod(trunc(O51/60),60)&" minutes" -> 0 days 0 hours 0 minutes | I51: 0 | M51: / | N51: =H51+G51*60+F51*3600+E51*86400 -> 0 | O51: =ROUNDUP(N51*(D51+1),0) -> 0
A52: Lumber Mill | B52: 1 | C52: =trunc(O52/86400)&" days "&mod(trunc(O52/3600),24)&" hours "&mod(trunc(O52/60),60)&" minutes" -> 0 days 0 hours 0 minutes | N52: =H52+G52*60+F52*3600+E52*86400 -> 0 | O52: =ROUNDUP(N52*(D52+1),0) -> 0
A53: Lumber Mill | B53: 2 | C53: =trunc(O53/86400)&" days "&mod(trunc(O53/3600),24)&" hours "&mod(trunc(O53/60),60)&" minutes" -> 0 days 0 hours 0 minutes | J53: 0 | M53: / | N53: =H53+G53*60+F53*3600+E53*86400 -> 0 | O53: =ROUNDUP(N53*(D53+1),0) -> 0
A54: Lumber Mill | B54: 3 | C54: =trunc(O54/86400)&" days "&mod(trunc(O54/3600),24)&" hours "&mod(trunc(O54/60),60)&" minutes" -> 0 days 0 hours 0 minutes | J54: 0 | M54: / | N54: =H54+G54*60+F54*3600+E54*86400 -> 0 | O54: =ROUNDUP(N54*(D54+1),0) -> 0
A55: Lumber Mill | B55: 4 | C55: =trunc(O55/86400)&" days "&mod(trunc(O55/3600),24)&" hours "&mod(trunc(O55/60),60)&" minutes" -> 0 days 0 hours 0 minutes | J55: 0 | M55: / | N55: =H55+G55*60+F55*3600+E55*86400 -> 0 | O55: =ROUNDUP(N55*(D55+1),0) -> 0
A56: Lumber Mill | B56: 5 | C56: =trunc(O56/86400)&" days "&mod(trunc(O56/3600),24)&" hours "&mod(trunc(O56/60),60)&" minutes" -> 0 days 0 hours 0 minutes | J56: 0 | M56: / | N56: =H56+G56*60+F56*3600+E56*86400 -> 0 | O56: =ROUNDUP(N56*(D56+1),0) -> 0
A57: Lumber Mill | B57: 6 | C57: =trunc(O57/86400)&" days "&mod(trunc(O57/3600),24)&" hours "&mod(trunc(O57/60),60)&" minutes" -> 0 days 0 hours 0 minutes | J57: 0 | M57: / | N57: =H57+G57*60+F57*3600+E57*86400 -> 0 | O57: =ROUNDUP(N57*(D57+1),0) -> 0
A58: Lumber Mill | B58: 7 | C58: =trunc(O58/86400)&" days "&mod(trunc(O58/3600),24)&" hours "&mod(trunc(O58/60),60)&" minutes" -> 0 days 0 hours 0 minutes | J58: 0 | M58: / | N58: =H58+G58*60+F58*3600+E58*86400 -> 0 | O58: =ROUNDUP(N58*(D58+1),0) -> 0
A59: Lumber Mill | B59: 8 | C59: =trunc(O59/86400)&" days "&mod(trunc(O59/3600),24)&" hours "&mod(trunc(O59/60),60)&" minutes" -> 0 days 0 hours 0 minutes | J59: 0 | M59: / | N59: =H59+G59*60+F59*3600+E59*86400 -> 0 | O59: =ROUNDUP(N59*(D59+1),0) -> 0
A60: Lumber Mill | B60: 9 | C60: =trunc(O60/86400)&" days "&mod(trunc(O60/3600),24)&" hours "&mod(trunc(O60/60),60)&" minutes" -> 0 days 0 hours 0 minutes | J60: 0 | M60: / | N60: =H60+G60*60+F60*3600+E60*86400 -> 0 | O60: =ROUNDUP(N60*(D60+1),0) -> 0
A61: Lumber Mill | B61: 10 | C61: =trunc(O61/86400)&" days "&mod(trunc(O61/3600),24)&" hours "&mod(trunc(O61/60),60)&" minutes" -> 0 days 0 hours 0 minutes | J61: 0 | M61: / | N61: =H61+G61*60+F61*3600+E61*86400 -> 0 | O61: =ROUNDUP(N61*(D61+1),0) -> 0
A62: Lumber Mill | B62: 11 | C62: =trunc(O62/86400)&" days "&mod(trunc(O62/3600),24)&" hours "&mod(trunc(O62/60),60)&" minutes" -> 0 days 3 hours 0 minutes | D62: 0.56 | E62: 0 | F62: 1 | G62: 55 | H62: 24 | I62: 13000 | J62: 0 | K62: 10000 | L62: 500 | M62: / | N62: =H62+G62*60+F62*3600+E62*86400 -> 6924 | O62: =ROUNDUP(N62*(D62+1),0) -> 10802
A63: Lumber Mill | B63: 12 | C63: =trunc(O63/86400)&" days "&mod(trunc(O63/3600),24)&" hours "&mod(trunc(O63/60),60)&" minutes" -> 0 days 0 hours 0 minutes | J63: 0 | M63: / | N63: =H63+G63*60+F63*3600+E63*86400 -> 0 | O63: =ROUNDUP(N63*(D63+1),0) -> 0
A64: Lumber Mill | B64: 13 | C64: =trunc(O64/86400)&" days "&mod(trunc(O64/3600),24)&" hours "&mod(trunc(O64/60),60)&" minutes" -> 0 days 0 hours 0 minutes | J64: 0 | M64: / | N64: =H64+G64*60+F64*3600+E64*86400 -> 0 | O64: =ROUNDUP(N64*(D64+1),0) -> 0
A65: Lumber Mill | B65: 14 | C65: =trunc(O65/86400)&" days "&mod(trunc(O65/3600),24)&" hours "&mod(trunc(O65/60),60)&" minutes" -> 0 days 0 hours 0 minutes | J65: 0 | M65: / | N65: =H65+G65*60+F65*3600+E65*86400 -> 0 | O65: =ROUNDUP(N65*(D65+1),0) -> 0
A66: Lumber Mill | B66: 15 | C66: =trunc(O66/86400)&" days "&mod(trunc(O66/3600),24)&" hours "&mod(trunc(O66/60),60)&" minutes" -> 0 days 0 hours 0 minutes | J66: 0 | M66: / | N66: =H66+G66*60+F66*3600+E66*86400 -> 0 | O66: =ROUNDUP(N66*(D66+1),0) -> 0
A67: Lumber Mill | B67: 16 | C67: =trunc(O67/86400)&" days "&mod(trunc(O67/3600),24)&" hours "&mod(trunc(O67/60),60)&" minutes" -> 0 days 0 hours 0 minutes | J67: 0 | M67: / | N67: =H67+G67*60+F67*3600+E67*86400 -> 0 | O67: =ROUNDUP(N67*(D67+1),0) -> 0
A68: Lumber Mill | B68: 17 | C68: =trunc(O68/86400)&" days "&mod(trunc(O68/3600),24)&" hours "&mod(trunc(O68/60),60)&" minutes" -> 0 days 0 hours 0 minutes | J68: 0 | M68: / | N68: =H68+G68*60+F68*3600+E68*86400 -> 0 | O68: =ROUNDUP(N68*(D68+1),0) -> 0
A69: Lumber Mill | B69: 18 | C69: =trunc(O69/86400)&" days "&mod(trunc(O69/3600),24)&" hours "&mod(trunc(O69/60),60)&" minutes" -> 0 days 22 hours 13 minutes | D69: 0.56 | E69: 0 | F69: 14 | G69: 14 | H69: 43 | I69: 235000 | J69: 0 | K69: 176000 | L69: 22000 | M69: / | N69: =H69+G69*60+F69*3600+E69*86400 -> 51283 | O69: =ROUNDUP(N69*(D69+1),0) -> 80002
A70: Lumber Mill | B70: 19 | C70: =trunc(O70/86400)&" days "&mod(trunc(O70/3600),24)&" hours "&mod(trunc(O70/60),60)&" minutes" -> 0 days 0 hours 0 minutes | J70: 0 | M70: / | N70: =H70+G70*60+F70*3600+E70*86400 -> 0 | O70: =ROUNDUP(N70*(D70+1),0) -> 0
A71: Lumber Mill | B71: 20 | C71: =trunc(O71/86400)&" days "&mod(trunc(O71/3600),24)&" hours "&mod(trunc(O71/60),60)&" minutes" -> 0 days 0 hours 0 minutes | J71: 0 | M71: / | N71: =H71+G71*60+F71*3600+E71*86400 -> 0 | O71: =ROUNDUP(N71*(D71+1),0) -> 0
A72: Lumber Mill | B72: 21 | C72: =trunc(O72/86400)&" days "&mod(trunc(O72/3600),24)&" hours "&mod(trunc(O72/60),60)&" minutes" -> 0 days 0 hours 0 minutes | J72: 0 | M72: / | N72: =H72+G72*60+F72*3600+E72*86400 -> 0 | O72: =ROUNDUP(N72*(D72+1),0) -> 0
A73: Lumber Mill | B73: 22 | C73: =trunc(O73/86400)&" days "&mod(trunc(O73/3600),24)&" hours "&mod(trunc(O73/60),60)&" minutes" -> 0 days 0 hours 0 minutes | J73: 0 | M73: / | N73: =H73+G73*60+F73*3600+E73*86400 -> 0 | O73: =ROUNDUP(N73*(D73+1),0) -> 0
A74: Lumber Mill | B74: 23 | C74: =trunc(O74/86400)&" days "&mod(trunc(O74/3600),24)&" hours "&mod(trunc(O74/60),60)&" minutes" -> 3 days 5 hours 46 minutes | D74: 0.71 | E74: 1 | F74: 21 | G74: 29 | H74: 3 | I74: 1900000 | J74: 0 | K74: 1400000 | L74: 170000 | M74: / | N74: =H74+G74*60+F74*3600+E74*86400 -> 163743 | O74: =ROUNDUP(N74*(D74+1),0) -> 280001
A75: Lumber Mill | B75: 24 | C75: =trunc(O75/86400)&" days "&mod(trunc(O75/3600),24)&" hours "&mod(trunc(O75/60),60)&" minutes" -> 4 days 1 hours 13 minutes | D75: 0.7 | E75: 2 | F75: 9 | G75: 11 | H75: 23 | I75: 3000000 | J75: 0 | K75: 2200000 | L75: 270000 | M75: / | N75: =H75+G75*60+F75*3600+E75*86400 -> 205883 | O75: =ROUNDUP(N75*(D75+1),0) -> 350002
A76: Lumber Mill | B76: 25 | C76: =trunc(O76/86400)&" days "&mod(trunc(O76/3600),24)&" hours "&mod(trunc(O76/60),60)&" minutes" -> 0 days 0 hours 0 minutes | J76: 0 | M76: / | N76: =H76+G76*60+F76*3600+E76*86400 -> 0 | O76: =ROUNDUP(N76*(D76+1),0) -> 0
A77: Foundry | B77: 1 | C77: =trunc(O77/86400)&" days "&mod(trunc(O77/3600),24)&" hours "&mod(trunc(O77/60),60)&" minutes" -> 0 days 0 hours 0 minutes | N77: =H77+G77*60+F77*3600+E77*86400 -> 0 | O77: =ROUNDUP(N77*(D77+1),0) -> 0
A78: Foundry | B78: 2 | C78: =trunc(O78/86400)&" days "&mod(trunc(O78/3600),24)&" hours "&mod(trunc(O78/60),60)&" minutes" -> 0 days 0 hours 0 minutes | K78: 0 | L78: 0 | M78: / | N78: =H78+G78*60+F78*3600+E78*86400 -> 0 | O78: =ROUNDUP(N78*(D78+1),0) -> 0
A79: Foundry | B79: 3 | C79: =trunc(O79/86400)&" days "&mod(trunc(O79/3600),24)&" hours "&mod(trunc(O79/60),60)&" minutes" -> 0 days 0 hours 0 minutes | K79: 0 | L79: 0 | M79: / | N79: =H79+G79*60+F79*3600+E79*86400 -> 0 | O79: =ROUNDUP(N79*(D79+1),0) -> 0
A80: Foundry | B80: 4 | C80: =trunc(O80/86400)&" days "&mod(trunc(O80/3600),24)&" hours "&mod(trunc(O80/60),60)&" minutes" -> 0 days 0 hours 0 minutes | K80: 0 | L80: 0 | M80: / | N80: =H80+G80*60+F80*3600+E80*86400 -> 0 | O80: =ROUNDUP(N80*(D80+1),0) -> 0
A81: Foundry | B81: 5 | C81: =trunc(O81/86400)&" days "&mod(trunc(O81/3600),24)&" hours "&mod(trunc(O81/60),60)&" minutes" -> 0 days 0 hours 0 minutes | K81: 0 | L81: 0 | M81: / | N81: =H81+G81*60+F81*3600+E81*86400 -> 0 | O81: =ROUNDUP(N81*(D81+1),0) -> 0
A82: Foundry | B82: 6 | C82: =trunc(O82/86400)&" days "&mod(trunc(O82/3600),24)&" hours "&mod(trunc(O82/60),60)&" minutes" -> 0 days 0 hours 0 minutes | K82: 0 | L82: 0 | M82: / | N82: =H82+G82*60+F82*3600+E82*86400 -> 0 | O82: =ROUNDUP(N82*(D82+1),0) -> 0
A83: Foundry | B83: 7 | C83: =trunc(O83/86400)&" days "&mod(trunc(O83/3600),24)&" hours "&mod(trunc(O83/60),60)&" minutes" -> 0 days 1 hours 10 minutes | D83: 0.71 | E83: 0 | F83: 0 | G83: 40 | H83: 57 | I83: 5300 | J83: 5300 | K83: 0 | L83: 0 | M83: / | N83: =H83+G83*60+F83*3600+E83*86400 -> 2457 | O83: =ROUNDUP(N83*(D83+1),0) -> 4202
A84: Foundry | B84: 8 | C84: =trunc(O84/86400)&" days "&mod(trunc(O84/3600),24)&" hours "&mod(trunc(O84/60),60)&" minutes" -> 0 days 0 hours 0 minutes | K84: 0 | L84: 0 | M84: / | N84: =H84+G84*60+F84*3600+E84*86400 -> 0 | O84: =ROUNDUP(N84*(D84+1),0) -> 0
A85: Foundry | B85: 9 | C85: =trunc(O85/86400)&" days "&mod(trunc(O85/3600),24)&" hours "&mod(trunc(O85/60),60)&" minutes" -> 0 days 0 hours 0 minutes | K85: 0 | L85: 0 | M85: / | N85: =H85+G85*60+F85*3600+E85*86400 -> 0 | O85: =ROUNDUP(N85*(D85+1),0) -> 0
A86: Foundry | B86: 10 | C86: =trunc(O86/86400)&" days "&mod(trunc(O86/3600),24)&" hours "&mod(trunc(O86/60),60)&" minutes" -> 0 days 2 hours 24 minutes | D86: 0.71 | E86: 0 | F86: 1 | G86: 24 | H86: 13 | I86: 17500 | J86: 17500 | K86: 0 | L86: 0 | M86: / | N86: =H86+G86*60+F86*3600+E86*86400 -> 5053 | O86: =ROUNDUP(N86*(D86+1),0) -> 8641
A87: Foundry | B87: 11 | C87: =trunc(O87/86400)&" days "&mod(trunc(O87/3600),24)&" hours "&mod(trunc(O87/60),60)&" minutes" -> 0 days 0 hours 0 minutes | K87: 0 | M87: / | N87: =H87+G87*60+F87*3600+E87*86400 -> 0 | O87: =ROUNDUP(N87*(D87+1),0) -> 0
A88: Foundry | B88: 12 | C88: =trunc(O88/86400)&" days "&mod(trunc(O88/3600),24)&" hours "&mod(trunc(O88/60),60)&" minutes" -> 0 days 0 hours 0 minutes | K88: 0 | M88: / | N88: =H88+G88*60+F88*3600+E88*86400 -> 0 | O88: =ROUNDUP(N88*(D88+1),0) -> 0
A89: Foundry | B89: 13 | C89: =trunc(O89/86400)&" days "&mod(trunc(O89/3600),24)&" hours "&mod(trunc(O89/60),60)&" minutes" -> 0 days 0 hours 0 minutes | K89: 0 | M89: / | N89: =H89+G89*60+F89*3600+E89*86400 -> 0 | O89: =ROUNDUP(N89*(D89+1),0) -> 0
A90: Foundry | B90: 14 | C90: =trunc(O90/86400)&" days "&mod(trunc(O90/3600),24)&" hours "&mod(trunc(O90/60),60)&" minutes" -> 0 days 0 hours 0 minutes | K90: 0 | M90: / | N90: =H90+G90*60+F90*3600+E90*86400 -> 0 | O90: =ROUNDUP(N90*(D90+1),0) -> 0
A91: Foundry | B91: 15 | C91: =trunc(O91/86400)&" days "&mod(trunc(O91/3600),24)&" hours "&mod(trunc(O91/60),60)&" minutes" -> 0 days 0 hours 0 minutes | K91: 0 | M91: / | N91: =H91+G91*60+F91*3600+E91*86400 -> 0 | O91: =ROUNDUP(N91*(D91+1),0) -> 0
A92: Foundry | B92: 16 | C92: =trunc(O92/86400)&" days "&mod(trunc(O92/3600),24)&" hours "&mod(trunc(O92/60),60)&" minutes" -> 0 days 0 hours 0 minutes | K92: 0 | M92: / | N92: =H92+G92*60+F92*3600+E92*86400 -> 0 | O92: =ROUNDUP(N92*(D92+1),0) -> 0
A93: Foundry | B93: 17 | C93: =trunc(O93/86400)&" days "&mod(trunc(O93/3600),24)&" hours "&mod(trunc(O93/60),60)&" minutes" -> 0 days 0 hours 0 minutes | K93: 0 | M93: / | N93: =H93+G93*60+F93*3600+E93*86400 -> 0 | O93: =ROUNDUP(N93*(D93+1),0) -> 0
A94: Foundry | B94: 18 | C94: =trunc(O94/86400)&" days "&mod(trunc(O94/3600),24)&" hours "&mod(trunc(O94/60),60)&" minutes" -> 0 days 0 hours 0 minutes | I94: 455000 | J94: 455000 | K94: 0 | M94: / | N94: =H94+G94*60+F94*3600+E94*86400 -> 0 | O94: =ROUNDUP(N94*(D94+1),0) -> 0
A95: Foundry | B95: 19 | C95: =trunc(O95/86400)&" days "&mod(trunc(O95/3600),24)&" hours "&mod(trunc(O95/60),60)&" minutes" -> 0 days 0 hours 0 minutes | K95: 0 | M95: / | N95: =H95+G95*60+F95*3600+E95*86400 -> 0 | O95: =ROUNDUP(N95*(D95+1),0) -> 0
A96: Foundry | B96: 20 | C96: =trunc(O96/86400)&" days "&mod(trunc(O96/3600),24)&" hours "&mod(trunc(O96/60),60)&" minutes" -> 0 days 0 hours 0 minutes | I96: 1000000 | J96: 1000000 | K96: 0 | L96: 96000 | M96: / | N96: =H96+G96*60+F96*3600+E96*86400 -> 0 | O96: =ROUNDUP(N96*(D96+1),0) -> 0
A97: Foundry | B97: 21 | C97: =trunc(O97/86400)&" days "&mod(trunc(O97/3600),24)&" hours "&mod(trunc(O97/60),60)&" minutes" -> 0 days 0 hours 0 minutes | K97: 0 | M97: / | N97: =H97+G97*60+F97*3600+E97*86400 -> 0 | O97: =ROUNDUP(N97*(D97+1),0) -> 0
A98: Foundry | B98: 22 | C98: =trunc(O98/86400)&" days "&mod(trunc(O98/3600),24)&" hours "&mod(trunc(O98/60),60)&" minutes" -> 0 days 0 hours 0 minutes | K98: 0 | M98: / | N98: =H98+G98*60+F98*3600+E98*86400 -> 0 | O98: =ROUNDUP(N98*(D98+1),0) -> 0
A99: Foundry | B99: 23 | C99: =trunc(O99/86400)&" days "&mod(trunc(O99/3600),24)&" hours "&mod(trunc(O99/60),60)&" minutes" -> 2 days 22 hours 0 minutes | D99: 0.71 | E99: 1 | F99: 16 | G99: 56 | H99: 9 | I99: 3500000 | J99: 3500000 | K99: 0 | L99: 320000 | M99: / | N99: =H99+G99*60+F99*3600+E99*86400 -> 147369 | O99: =ROUNDUP(N99*(D99+1),0) -> 252001
A100: Foundry | B100: 24 | C100: =trunc(O100/86400)&" days "&mod(trunc(O100/3600),24)&" hours "&mod(trunc(O100/60),60)&" minutes" -> 3 days 21 hours 20 minutes | D100: 0.7 | E100: 2 | F100: 6 | G100: 54 | H100: 8 | I100: 5400000 | J100: 5400000 | K100: 0 | L100: 500000 | M100: / | N100: =H100+G100*60+F100*3600+E100*86400 -> 197648 | O100: =ROUNDUP(N100*(D100+1),0) -> 336002
A101: Foundry | B101: 25 | C101: =trunc(O101/86400)&" days "&mod(trunc(O101/3600),24)&" hours "&mod(trunc(O101/60),60)&" minutes" -> 0 days 0 hours 0 minutes | K101: 0 | M101: / | N101: =H101+G101*60+F101*3600+E101*86400 -> 0 | O101: =ROUNDUP(N101*(D101+1),0) -> 0
...

Sheet Lei Kuan Scaling HP
A1: Current Legion | B1: HP | C1: Damage | D1: Damage Flat | E1: ATK | G1: Target HP | H1: Target DEF | I1: Target HS Reduc | J1: Target Reduc flat
A2: 242128 | B2: 21 | C2: 1264 | D2: 1 | G2: -20 | H2: =42 -> 42 | L2: 1 | M2: 2 | N2: 3 | O2: 4 | P2: 5 | Q2: 6 | R2: 7 | S2: 8 | T2: 9 | U2: 10 | V2: 11 | W2: 12 | X2: 13 | Y2: 14 | Z2: 15
A3: 237377 | B3: 45 | C3: 1532 | G3: -40 | H3: 42 | I3: -8 | J3: -20 | L3: M | N3: D | P3: P | Q3: c | R3: c | S3: c
A4: 233642 | B4: 50 | C4: 1701 | G4: -50 | H4: 43.5 | I4: -8 | J4: -20
A5: 229856 | B5: 51 | C5: 1563 | D5: 1 | G5: -50 | H5: 45 | I5: -8
A6: 225327 | B6: 52 | C6: 1611 | D6: 2 | G6: -45 | H6: 50
A7: 221458 | B7: 50 | C7: 1290 | G7: -50 | H7: 50.5 | J7: -20
A8: 217716 | B8: 52 | C8: 1326 | D8: 2 | G8: -50 | H8: 48 | J8: -20
A9: 214114 | B9: 52 | C9: 1191 | D9: 2 | G9: -50 | H9: 48 | I9: -8 | J9: -20
A10: 209302 | B10: 53 | C10: 1170 | D10: 3 | G10: -50 | H10: 53.5 | J10: -20
A11: 205394 | B11: 57 | C11: 1306 | D11: 7 | G11: -45 | H11: 54.5 | J11: -20
A12: 201642 | B12: 50 | C12: 1159 | G12: -45 | H12: 54.5 | J12: -20
A13: 198020 | B13: 50 | C13: 1095 | G13: -50 | H13: 49.5 | J13: -20
A14: 193915 | B14: 51 | C14: 1219 | D14: 1 | G14: -50 | H14: 49.5 | J14: -20
A15: 190555 | B15: 50 | C15: 1289 | G15: -45 | H15: 54.5 | I15: -8
A16: 187304 | B16: 52 | C16: 1504 | D16: 2 | G16: -50 | H16: 49.5
A17: 183971 | B17: 50 | C17: 1267 | G17: -45 | H17: 54.5 | I17: -8
A18: 180895 | B18: 50 | C18: 1326 | G18: -50 | H18: 49.5 | I18: -8
A21: BOGO REPORT 2
A22: 250839 | B22: 0 | C22: 675 | G22: 5 | H22: 54.5 | I22: -8 | J22: -20
A23: 247194 | B23: 20 | C23: 964 | G23: -15 | H23: 54.5 | J23: -20
A24: 243498 | B24: 40 | C24: 1197 | G24: -40 | H24: 49.5 | J24: -20
A25: 240749 | B25: 50 | C25: 1144 | G25: -45 | H25: 54.5 | I25: -8 | J25: -20
A26: 238370 | B26: 50 | C26: 1650 | E26: =C26/A26*1000 -> 6.922012 | G26: -50 | H26: 49.5
A27: 235944 | B27: 51 | C27: 1664 | D27: 1 | E27: =C27/A27*1000 -> 7.0525209 | G27: -50 | H27: 49.5
A28: 233613 | B28: 51 | C28: 1656 | D28: 1 | E28: =C28/A28*1000 -> 7.0886466 | G28: -50 | H28: 49.5
A29: 231040 | B29: 51 | C29: 1647 | D29: 1 | E29: =C29/A29*1000 -> 7.1286357 | G29: -50 | H29: 49.5
A30: 228687 | B30: 51 | C30: 1198 | G30: -50 | H30: 49.5 | I30: -8 | J30: -20
A31: 226531 | B31: 50 | C31: 1228 | G31: -50 | H31: 54.5 | J31: -20
A32: 224580 | B32: 52 | C32: 1263 | G32: -45 | H32: 54.5 | J32: -20
A33: 221839 | B33: 52 | C33: 1325 | G33: -50 | H33: 49.5 | J33: -20
A34: 219858 | B34: 51 | C34: 1298 | G34: -50 | H34: 49.5 | J34: -20
A35: 218000 | B35: 50 | C35: 1455 | E35: =C35/A35*1000 -> 6.6743119 | F35: =E35/B35 -> 0.13348624 | G35: -50 | H35: 49.5 | I35: -8
A36: 216083 | B36: 50 | C36: 1449 | E36: =C36/A36*1000 -> 6.7057566 | F36: =E36/B36 -> 0.13411513 | G36: -50 | H36: 49.5 | I36: -8
A37: 214085 | B37: 50 | C37: 1437 | E37: =C37/A37*1000 -> 6.7122872 | F37: =E37/B37 -> 0.13424574 | G37: -50 | H37: 49.5 | I37: -8
A38: 212498 | B38: 53 | C38: 1501 | D38: 3 | E38: =C38/A38*1000 -> 7.0635959 | F38: =E38/B38 -> 0.13327539 | G38: -50 | H38: 49.5 | I38: -8
A39: 211058 | B39: 50 | C39: 1115 | G39: -50 | H39: 53.5 | I39: -8 | J39: -20
A40: 209476 | B40: 52 | C40: 1220 | D40: 2 | G40: -45 | H40: 54.5 | J40: -20
A41: 208093 | B41: 54 | C41: 1203 | D41: 4 | G41: -50 | H41: 49.5 | I41: -8 | J41: -20
A42: 206518 | B42: 54 | C42: 1173 | G42: -45 | H42: 54.5 | J42: -20
A43: 205264 | B43: 53 | C43: 1574 | D43: 3 | G43: -50 | H43: 53.5
A44: 203940 | B44: 51 | C44: 1428 | D44: 1 | G44: -50 | H44: 49.5 | I44: -8
A45: 202487 | B45: 20 | C45: 872 | G45: -20 | H45: 49.5 | J45: -20
A47: Bogo Darkling
C48: 10 | E48: 7
A49: LegionSize | B49: HP_Bonus | C49: DamageScaledOnHP | D49: NormalDamage | E49: Target_HP%_Debuff
A50: 303097 | B50: 31 | C50: 39 | D50: 24 | E50: -20
A51: 298315 | B51: 42.5 | C51: 51 | D51: 27 | E51: -40
A52: 295491 | B52: 53 | C52: 57 | D52: 30 | E52: -50
A53: 268702 | B53: 23 | C53: 36 | D53: 24 | E53: -20
A54: 267498 | B54: 43 | C54: 48 | D54: 27 | E54: -40
A55: 266577 | B55: 53 | C55: 54 | D55: 27 | E55: -40 | J55: 1700 | K55: =J55*(1+0.4*50/100) -> 2040
C59: 25 | E59: 32
A60: LegionSize | B60: HP_Bonus | C60: DamageScaledOnHP | D60: NormalDamage | E60: Target_HP%_Debuff
A61: 240604 | B61: 23 | C61: 25 | D61: 32 | E61: 0
A62: 187168 | B62: 138 | C62: 63 | D62: 41 | E62: -20
A63: 180309 | B63: 183 | C63: 76 | D63: 42 | E63: -40
A64: 179355 | B64: 123 | C64: 66 | D64: 46 | E64: -40
A65: 163275 | B65: 118 | C65: 55 | D65: 39 | E65: -50
A66: 160104 | B66: 13 | C66: 18 | D66: 25 | E66: 0
A67: 155498 | B67: 53 | C67: 33 | D67: 33 | E67: -20

Sheet Feuille 20
B1: 1 | C1: 2 | D1: 3 | E1: 4 | F1: 5 | G1: 6 | H1: 7 | I1: 8 | J1: 9 | K1: 10 | L1: 11 | M1: 12 | N1: 13 | O1: 14 | P1: 15 | Q1: 16 | R1: 17 | S1: 18 | T1: 19 | U1: 20 | V1: 21 | W1: 22 | X1: 23 | Y1: 24 | Z1: 25
A2: S | B2: O | C2: O | D2: O | E2: O | F2: O | G2: O | H2: O | M2: O | N2: O | O2: O | P2: O | Q2: O | R2: O | S2: O
A3: F | D3: O | E3: O | F3: O | G3: O | H3: O | I3: O | J3: O | O3: O | P3: O | Q3: O | R3: O | S3: O | T3: O | U3: O
A4: W | G4: O | H4: O | I4: O | J4: O | K4: O | L4: O | M4: O | R4: O | S4: O | T4: O | U4: O | V4: O | W4: O | X4: O

Sheet Feuille 19
B1: Power 15:40 | C1: Merits 15:40 | D1: Power 21:22 | E1: Merits 21:22 | F1: Power 23:49 | G1: Merits 23:49 | H1: Power 5:00 => 18:00 | I1: Merits 5:00 => 18:00
A2: PB | B2: 7267411153 | C2: 332037045 | D2: 7322560183 | E2: 350439973 | F2: 7139517492 | G2: 374079785
A3: E:86 | B3: 5715053934 | C3: 145696594 | D3: 5894917359 | E3: 166604907 | F3: 5737534942 | G3: 189952309
B8: 1m | C8: 5m
A9: 1880 | B9: 286 | C9: 6 | D9: =B9+C9*5 -> 316 | E9: =D9/A9 -> 0.16808511
A11: 100 | B11: 500 | C11: 1000
A12: 400 | B12: 36 | C12: 8 | D12: =A11*A12+B11*B12+C11*C12 -> 66000 | E12: =D12/20150*100*30 -> 9826.3027 | F12: =E12/60 -> 163.77171
A13: 71 | B13: 114 | C13: 0 | D13: =A11*A13+B11*B13+C11*C13 -> 64100
A15: BP | B15: =4+5+6+4+8 -> 27
A16: Season (42d) | B16: =6*5 -> 30
B17: =SUM(B15:B16) -> 57
G18: 385 | H18: 97250
A19: 40 | B19: 150 | D19: =(50+48+46+44+42+(40*95))/100 -> 40.3 | G19: 525000 | H19: =H18/2100 -> 46.309524
A20: 1100 | B20: 4000 | H20: =1600*H19*10 -> 740952.38
A21: =D12/A19*A20 -> 1815000 | B21: =D12/B19*B20 -> 1760000 | G21: =G19+H20 -> 1265952.4
A25: =4000/150 -> 26.666667 | B25: =1100/40.3 -> 27.295285
G26: 5464 | H26: 4756 | I26: =G26-H26 -> 708 | K26: =3369+3567 -> 6936
G27: 16638 | H27: 13098 | I27: =G27-H27 -> 3540 | K27: =3637+3851 -> 7488
A28: 30 | B28: 2.8 | C28: =B28/A28 -> 0.093333333 | D28: =21860*C28 -> 2040.2667 | G28: 3636 | H28: 2928 | I28: =G28-H28 -> 708
A29: 210 | B29: 10 | C29: =B29/A29 -> 0.047619048 | D29: =117000*C28 -> 10920 | G29: 11970 | H29: 9279 | I29: =G29-H29 -> 2691
C30: =B30/A30 -> #DIV/0! | D30: =33000*C28 -> 3080 | I30: =sum(I26:I29) -> 7647 | K30: 1250 | L30: 5
C31: =(C30+C28)/2 -> #DIV/0! | D31: =423310*C28 -> 39508.933 | K31: =I33/K30*L30 -> 2100
G32: 2100 | H32: 16000 | I32: 4000000
I33: =I32/H32*G32 -> 525000

Sheet AH
A1: Name | B1: Auction Price | C1: Auction Price | D1: Shop Price | E1: Selling Price | F1: Profit
A2: Angry Roar 2* | B2: 12320 | C2: =B2*1.1 -> 13552 | D2: 27249 | E2: =D2*0.8 -> 21799.2 | F2: =E2-C2 -> 8247.2
A3: Fatal Bite 2 | B3: 19842 | C3: =B3*1.1 -> 21826.2 | D3: 28000 | E3: =D3*0.8 -> 22400 | F3: =E3-C3 -> 573.8 | I3: Avant | J3: Après | K3: Profit
A4: Intense Counter 2 | B4: 3168 | C4: =B4*1.1 -> 3484.8 | D4: 3920 | E4: =D4*0.8 -> 3136 | F4: =E4-C4 -> -348.8 | H4: Necro | I4: 33775 | J4: =29477+21294 -> 50771 | K4: =J4-I4 -> 16996
A5: Fierce Attack 2 | B5: 4218 | C5: =B5*1.1 -> 4639.8 | D5: 7020 | E5: =D5*0.8 -> 5616 | F5: =E5-C5 -> 976.2 | H5: Magma | I5: 52449 | J5: 64353 | K5: =J5-I5 -> 11904
A6: Intense Fierce Attack 2 | B6: 4542 | C6: =B6*1.1 -> 4996.2 | D6: 6344 | E6: =D6*0.8 -> 5075.2 | F6: =E6-C6 -> 79 | H6: Dragon | I6: 68154 | J6: 82421 | K6: =J6-I6 -> 14267
A7: Chain strike 2 | B7: 4218 | C7: =B7*1.1 -> 4639.8 | D7: 6845 | E7: =D7*0.8 -> 5476 | F7: =E7-C7 -> 836.2
A8: Magic Fortune 2 | B8: 14908 | C8: =B8*1.1 -> 16398.8 | D8: 21722 | E8: =D8*0.8 -> 17377.6 | F8: =E8-C8 -> 978.8
A9: Intense Infection 2 | B9: 16399 | C9: =B9*1.1 -> 18038.9 | D9: 24839 | E9: =D9*0.8 -> 19871.2 | F9: =E9-C9 -> 1832.3
A10: Intense Shadow Hunter 2 | B10: 13552 | C10: =B10*1.1 -> 14907.2 | D10: 17734 | E10: =D10*0.8 -> 14187.2 | F10: =E10-C10 -> -720
A11: Intense Puncture 2 | B11: 12320 | C11: =B11*1.1 -> 13552 | D11: 18618 | E11: =D11*0.8 -> 14894.4 | F11: =E11-C11 -> 1342.4
A12: Intense Outburst 2 | B12: 11200 | C12: =B12*1.1 -> 12320 | D12: 14759 | E12: =D12*0.8 -> 11807.2 | F12: =E12-C12 -> -512.8
E17: Total | F17: =sum(F2:F16) -> 13284.3
A22: 11400 gem
A23: 90j speedup
A24: 2 relocate

Sheet Feuille 23
A1: 45838.5 | B1: 45855.111
A3: {=A1 + SEQUENCE(10, 1, 0, 1) * 86 / 24} -> 45838.5 | B3: {=B1 + SEQUENCE(10, 1, 0, 1) * 72 / 24} -> 45855.111
A4: 45842.083 | B4: 45858.111
A5: 45845.667 | B5: 45861.111
A6: 45849.25 | B6: 45864.111
A7: 45852.833 | B7: 45867.111
A8: 45856.417 | B8: 45870.111
A9: 45860 | B9: 45873.111
A10: 45863.583 | B10: 45876.111
A11: 45867.167 | B11: 45879.111
A12: 45870.75 | B12: 45882.111

Sheet Test formula
A1: 300000 | D1: troopSize | F1: expected: | G1: 1824
A2: 452 | B2: =A2 * (1 + A3 / 100) -> 1476.684 | D2: ATK
A3: 226.7 | D3: ATK Buff (%)
A4: 170 | B4: =A4 * (1 + (A5 / 100) - (A12 / 100) ) -> 341.7 | D4: enemyDEF
A5: 103 | D5: enemyDEF Buff (%)
A6: 211 | B6: =A6 * (1 + (A7 / 100) - (A13 / 100) ) -> 369.039 | D6: enemyHP
A7: 78.2 | D7: enemyHP Buff (%)
A8: 2 | D8: damageFactor
A9: 40 | B9: =A9/100 -> 0.4 | D9: Normal Damage Buff (%)
A10: 11.5 | B10: =A10/100 -> 0.115 | D10: Flat Damage Buff (%)
A11: 300000 | D11: troopMaxSize
A12: 2 | D12: Ignore DEF
A13: 3.3 | D13: Ignore HP
A15: Total | B15: =(((A1 * B2) / (B4 * B6)) * A8) * (1 + A9 / 100) * (1 + A10 / 100) -> 10967.925 | F15: =SQRT(10000/300000) -> 0.18257419
B16: =(((A1 * B2 * (1 + B9+B10)) / (B4 * B6)) * A8) *F15 -> 1943.4509
A18: =ROUNDUP((((((((A1*((A2*(100%+A3))*(100%+A9))))/(A4*(100%+A5)))/(A6*(100%+A7)))*2)*sqrt(10000/A1))),0) -> 1565

Sheet Brink of War
A1: CP
A2: Size | B2: 100 | C2: 500 | D2: 1000 | E2: Total
A3: Qty | B3: 292 | C3: 137 | D3: 5 | E3: =B2*B3+C2*C3+D2*D3 -> 102700
A4: Qty 2 | B4: 0 | C4: 48 | D4: 0 | E4: =B2*B4+C2*C4+D2*D4 -> 24000
A6: Shadow Trolls
B7: CP | C7: Points | D7: Points / CP
A8: Elite (Rally) | B8: 150 | C8: 4000 | D8: =C8/B8 -> 26.666667
A9: Normal | B9: 50 | C9: 1100 | D9: =C9/B9 -> 22
A10: Normal (Min) | B10: 40 | C10: 1100 | D10: =C10/B10 -> 27.5
A11: Normal x 100 (Auto) | B11: =(50+48+46+44+42+(40*95))*5 -> 20150 | C11: =C9*100*5 -> 550000 | D11: =C11/B11 -> 27.295285
A12: Normal x 100 (Auto) | B12: =(50+48+46+44+42+(40*(C13-5)))*5 -> 4950 | C12: =C10*C13*5 -> 132000 | D12: =C12/B12 -> 26.666667
C13: 24

Sheet Artifacts
A1: Name | B1: Main Stats | C1: MS Min | D1: MS Max | E1: Secondary Stats | F1: SS Min | G1: SS Max | H1: Quality | I1: Category 1 | J1: Category 2 | K1: Category 3 | L1: Cooldown | M1: Rage Cost | N1: Ability Name | O1: Ability Description | P1: Ability Upgrade | Q1: Season
A2: Sorland's Blade | B2: Cavalry Unit ATK | C2: 5 | D2: 40 | E2: Legion March Speed | F2: 4 | G2: 18 | H2: legendary | I2: Cavalry | J2: PvP | K2: Assault | L2: 1m30 | M2: 600 | N2: Sword Oath | O2: Deals damage to up to 2 enemy Legions in a designated arc. Damage Type: Artifact Skill Damage (Physical) Damage Factor: 1600 Targets take 25% less damage per additional target. Your Legion gains Haste: March Speed +20% for 10s. | P2: Skill Damage Factor: 1600/2000/2400/2800/3200 | Q2: 1
A3: Dragonrift | B3: Infantry Unit ATK | C3: 5 | D3: 40 | E3: Legion ATK | F3: 4 | G3: 22 | H3: legendary | I3: Infantry | J3: PvP | K3: Assault | L3: 1m30 | M3: 400 | N3: Dragon Tamer | O3: Deals damage to the selected Legion. Damage Type: Artifact Skill Damage (Physical) Damage Factor: 2000 If this Skill defeats the target, your Legion gains Physical Keen: Physical ATK +16% for 6s If this Skill does not defeat the target, they gain Bleed: deals damage every second for 3s. Damage Type: Artifact Skill Damage (Physical) Damage Factor: 150 | P3: Skill Damage Factor: 2000/2500/3000/3500/4000 Physical ATK bonus: 16%/20%/24%/28%/32% Skill Damage Factor: 150/200/250/300/350 | Q3: 1
A4: Ancient Tree Roots | B4: Overall Gather Speed | C4: 8 | D4: 40 | E4: Legion HP | F4: 4 | G4: 17 | H4: legendary | I4: Gathering | J4: / | K4: / | L4: 2m | M4: 0 | N4: Geomancy | O4: After a short charge-up, teleports your Legion to a random unmanned high-level Resource Point within range. Moving, being attacked, or gaining control effects interrupts.charge-up. | P4: Cooldown (seconds): 120/100/80/60/30 | Q4: 1
A5: Kurrata's Wrath | B5: Peacekeeping Damage | C5: 8 | D5: 40 | E5: Legion ATK | F5: 4 | G5: 22 | H5: legendary | I5: Peacekeeping | J5: / | K5: / | L5: 1m30 | M5: 0 | N5: Wolf Pack | O5: Grants a buff to up to 10 friendly Legions in a designated circle. Buff Effect: Damage dealt to Darklings and Dark Creatures +20% for 10s. | P5: Damage dealth during Peacekeeping bonus: 20%/25%/30%/35%/40% | Q5: 1
A6: Bloodblade Banner | B6: Rallied Army ATK | C6: 5 | D6: 40 | E6: Legion DEF | F6: 4 | G6: 22 | H6: legendary | I6: Rally | J6: Assault | K6: / | L6: 0 | M6: 0 | N6: Warrior Spirit | O6: While in battle, your Rallied Army deals damage and gains Physical Keen every 30s. Damage Type: Artifact Skill Damage (Physical): 650 Physical Keen: Physical ATK +5% for 10s. | P6: Skill Damage Factor: 650/800/950/1100/1300 Physical ATK bonus: 5%/6%/7%/8.5%/10% | Q6: 1
A7: Tear of Arbon | B7: Magic Unit DEF | C7: 5 | D7: 40 | E7: Legion DEF | F7: 4 | G7: 22 | H7: legendary | I7: Magic | J7: PvP | K7: Support | L7: 1m30 | M7: 1600 | N7: Divine Mercy | O7: Heals lightly wounded units once every 2s. Casts on up to 4 friendly Legions in a designated circle. Healing Factor: 400 Healing Duration: 8s | P7: Healing Factor: 400/500/600/700/800 | Q7: 1
A8: Phoenix Eye | B8: Magic Unit ATK | C8: 5 | D8: 40 | E8: Legion ATK | F8: 4 | G8: 22 | H8: legendary | I8: Magic | J8: PvP | K8: Assault | L8: 1m30 | M8: 1600 | N8: Burst Strike | O8: Deals damage to up to 4 enemy Legions in a designated circle. Damage Type: Artifact Skill Damage (Magic) Damage Factor: 2000 Legions take 15% less damage per additional target. | P8: Skill Damage Factor: 2000/2500/3000/3500/4000 Max targets: 4/4/4/4/5 | Q8: 1
A9: Fang of Ashkari | B9: Legion DEF | C9: 5 | D9: 40 | E9: Legion DEF | F9: 4 | G9: 22 | H9: legendary | I9: All-Rounder | J9: PvP | K9: Tank | L9: 1m30 | M9: 400 | N9: Thundershadow | O9: Sets a circle fixed at your Legion's location when cast. Deals damage every 2s to up to 4 enemy Legions within the circle. Damage Type: Artifact Skill Damage (Physical/Magic) Damage Factor: 500 Duration: 8s. Target take 15% less damage per additional target. | P9: Skill Damage Factor: 500/600/700/850/1000 | Q9: 1
A10: Heart of Kamasi | B10: Marksman Unit DEF | C10: 5 | D10: 40 | E10: Legion DEF | F10: 4 | G10: 22 | H10: legendary | I10: Marksman | J10: PvP | K10: Support | L10: 1m30 | M10: 1200 | N10: Earthen Judgment | O10: Grants your Legion and 2 nearby friendly Legions: 1) Physical Keen: Physical ATK +15% 2) Onslaught: normal attack damage dealt +15% Duration: 10s Only takes effect when leading a Marksman Legion. | P10: Physical ATK bonus: 15%/18%/22%/26%/30% Normal attack damage bonus: 15%/18%/22%/26%/30% | Q10: 1
A11: Wolf-Woman of Haelor | B11: Cavalry Unit HP | C11: 5 | D11: 38 | E11: Legion HP | F11: 4 | G11: 17 | H11: legendary | I11: Cavalry | J11: Mobility | K11: / | L11: 1m30 | M11: 0 | N11: Wolfshadow | O11: Select an empty area within range to teleport your Legion to that location. 15s later, or when the Skill is recast, your Legion will return to its original location. The first enemy Legion that your Legion attacked after the Skill was cast takes additional damage. Range: 18 Damage: 15% of damage dealt to that Legion after the Skill was cast | P11: Range: 18/21/24/27/30 Additional Damage Factor: 15%/18%/21%/25%/30% | Q11: 1
A12: Shadowblades | B12: Marksman Unit ATK | C12: 5 | D12: 40 | E12: Legion ATK | F12: 4 | G12: 22 | H12: legendary | I12: Marksman | J12: PvP | K12: Assault | L12: 1m30 | M12: 1200 | N12: Shadow Games | O12: Deals damage to up to 5 enemy Legions in a designated rectangle. Damage Type: Artifact Skill Damage (Physical) Damage Factor: 1800 Target take 15% less damage per additional target. | P12: Skill Damage Factor: 1800/2200/2600/3000/3600 | Q12: 1
A13: Springs of Silence | B13: Infantry Unit ATK | C13: 5 | D13: 40 | E13: Legion ATK | F13: 4 | G13: 22 | H13: legendary | I13: Infantry | J13: PvP | K13: Control | L13: 1m30 | M13: 400 | N13: Fleeting Beauty | O13: Deals diffused damage to up to 3 enemy Legions in a designated arc. Damage Type: Physical Damage Factor: 1600 Damaged targets are Slowed: March Speed -60% for 10s. | P13: Skill Damage Factor: 1600/2000/2400/2800/3200 | Q13: 1
A14: Lucia's Horn | B14: Overall Gather Speed | C14: 8 | D14: 26 | E14: Legion DEF | F14: 4 | G14: 22 | H14: legendary | I14: Gathering | J14: / | K14: / | L14: 2h | M14: 0 | N14: Bounty of Nature | O14: After a short charge-up, a random Resource Point located in Alliance territory near your Legion. Resource Point Minimum Level: 4 Resource Point Maximum Level: 5. Charge-up cannot be interrupted.. | P14: Resource Point minimum Level: 4/4/5/6/7 Resource Point max Level: 5/6/6/7/7 | Q14: 1
A15: Breath of the Forest | B15: Garrisoned Army ATK | C15: 5 | D15: 40 | E15: Legion DEF | F15: 4 | G15: 22 | H15: legendary | I15: Garrison | J15: Support | K15: / | L15: 0 | M15: 0 | N15: Deepwood Symphony | O15: When you are Garrison Captain of a City or Stronghold, randomly grants your Legion one of the following effects every 30s while in battle. Ode: Heals once every 2s. Healing Factor: 300 Healing Duration: 10s Hymn: Grand Vigor for 10s. Effect: HP +15% Aria: Removes one debuff every 2s. Duration: 6s | P15: Healing Factor: 300/370/440/520/600 HP Bonus: 15%/18%/22%/26%/30% | Q15: 1
A16: Infernal Flame | B16: Magic Unit ATK | C16: 5 | D16: 40 | E16: Legion ATK | F16: 4 | G16: 22 | H16: legendary | I16: Magic | J16: PvP | K16: Assault | L16: 1m30 | M16: 1600 | N16: Terrifying Inferno | O16: When cast, your Legion deals additional damage whenever they launch a normal attack. Damage Type: Artifact Skill Damage (Magic) Damage Factor: 1100 Effect Duration: 3s Passive: Your Legion gains Magic Keen when the wielder inflicts Scorch on enemies. Magic Keen: ATK +15% for 5s This effect can be triggered once every 10s. | P16: Additional Magic Skill Damage Factor: 1100/1350/1600/1900/2200 Magic ATK bonus: 15%/18%/21%/25%/30% | Q16: 2
A17: Kingslayer | B17: Cavalry Unit ATK | C17: 5 | D17: 40 | E17: Legion ATK | F17: 4 | G17: 22 | H17: legendary | I17: Cavalry | J17: PvP | K17: Assault | L17: 1m30 | M17: 600 | N17: Royal Punishment | O17: Deals damage to up to 5 enemy Lgions in a designated arc. Damage Type: Artifact Skill Damage (Physical) Damage Factor: 1800 Targets take 15% less damage per additional target. If the target is another Lord's Legion and has fewer than 10% units remaining, it is immediately defeated. | P17: Skill Damage Factor: 1800/2200/2600/3000/3600 | Q17: 1
A18: Springbird Feather | B18: Legion March Speed | C18: 7.5 | D18: 37.5 | E18: Legion HP | F18: 4 | G18: 17 | H18: legendary | I18: Mobility | J18: / | K18: / | L18: 1m30 | M18: 0 | N18: Mighty Tailwind | O18: Grants your Legion and 10 surrounding friendly Legions Haste for 10s. Your Legion: March Speed +24% Friendly Legions: March Speed +16% | P18: Legion March Speed bonus: 24%/30%/36%/42%/48% Friendly Legion March Speed bonus: 16%/20%/24%/28%/32% | Q18: 1
A19: Storm Arrows | B19: Cavalry Unit ATK | C19: 5 | D19: 40 | E19: Legion ATK | F19: 4 | G19: 22 | H19: legendary | I19: Cavalry | J19: Mobility | K19: / | L19: 1m30 | M19: 0 | N19: Blink | O19: Immediately teleports your Legion to a designated empty area. Teleport Range: 15 Your Legion gains Rampage: damage dealth +12% for 4s. | P19: Range: 15/18/21/25/30 Damage bonus: 12%/15%/18%/21%/24% | Q19: 1
A20: Visage of the Sanctus | B20: Flying Unit DEF | C20: 5 | D20: 40 | E20: Legion ATK | F20: 4 | G20: 22 | H20: legendary | I20: Flying | J20: PvP | K20: Tank | L20: 1m30 | M20: 600 | N20: Strike of the Light | O20: Consecutively grants 3 Boon Shields to a selected friendly Legion. Boon Shield Factor: 900 each time Boon Shield Duration: 10s Passive: Grants 1 stack of Mark of Judgment to the wielder when they grant a shield to themselves or any friendly Legion. Mark of Judgment: Stacks up to 10 times. Casting a Rage Skill triggers Supreme Judgment and clears all Mark of Judgment stacks. Supreme Judgment: Deals damage to the target Legion. Damage Type: Artifact Skill Damage Damage Factor 250 per stack Mark of Jugdgment stacks a cleared after battle ends. | P20: Boon Shield Factor: 900/1100/1300/1550/1800 Damage Factor: 250/310/370/430/500 | Q20: 2
A21: Staff of the Prophet | B21: Magic Unit HP | C21: 5 | D21: 33 | E21: Legion HP | F21: 4 | G21: 17 | H21: legendary | I21: Magic | J21: Mobility | K21: / | L21: 8h | M21: 0 | N21: Toward the Light | O21: Select a friendly Legion within the current Region. After a 6s charge-up, your Legion and 5 nearby friendly Legions are teleported to the target's location. Your Legions will be prioritized for teleportation ahead of any other friendly Legions.If the target is within Alliance territory, cooldown is greatly reduced. | P21: Cooldown (hours): 7/6/5/4/3 | Q21: 1
A22: Dragonscale Armor | B22: Infantry Unit HP | C22: 5 | D22: 33 | E22: Legion HP | F22: 4 | G22: 17 | H22: legendary | I22: Infantry | J22: PvP | K22: Tank | L22: 1m30 | M22: 400 | N22: Entangling Flames | O22: Grants a Boon Shield to your Legion. Grants Keen to up to 3 friendly Legions in a designated circle. Boon Shield Factor: 2200 Boon Shield Duration: 10s Keen: ATK +10% for 10s Passive: Your Legion gains Ranged Resistance when the wielder gains a shield through Rage Skills. Ranged Resistance: Ranged Damage taken -9% for 5s | P22: Shield Factor: 2200/2700/3300/3900/4500 Damage Taken From Ranged Unit Reduction: 9%/11%/13%/15%/18% | Q22: 2
A23: Rattle-Spear | B23: Marksman Unit ATK | C23: 5 | D23: 40 | E23: Legion ATK | F23: 4 | G23: 22 | H23: legendary | I23: Marksman | J23: PvP | K23: Assault | L23: 1m30 | M23: 1200 | N23: Vicious Strike | O23: Strikes three times in a designated arc. The first strike has a short charge-up. The direction of subsequent strikes can change depending on the target's location.. Damage Type: Artifact Skill Damage (Physical) Damage Factor: 1200 Inflicts Slow: March Speed -20% for 3s. Additional Effect: When your Legion inflicts DEF Break on an enemy Legion, your Legion gains DEF Penetration: ignore 10% of the enemy's DEF for 7s. | P23: Skill Damage Factor: 1200/1500/1800/2100/2500 DEF Penetration: 10%/12%/14%/17%/20% | Q23: 2
A24: Cloak of Stealth | B24: Cavalry Unit ATK | C24: 3 | D24: 28 | E24: Legion ATK | F24: 3 | G24: 18 | H24: epic | I24: Cavalry | J24: Mobility | K24: / | L24: 1h | M24: 0 | N24: Subterfuge | O24: Grants your Legions Stealth: March Speed -15% for 300s. While in Stealth, Legions can only be detected if they move too close to the enemy. Launching attacks, taking damage, or opening Chests will cause Stealth to expire. | P24: Duration: 300/600/900/1300/1800 March Speed reduction: 25%/25%/25%/25%/15% | Q24: 1
A25: Heartpiercer | B25: Marksman Unit ATK | C25: 3 | D25: 28 | E25: Legion ATK | F25: 3 | G25: 18 | H25: epic | I25: Marksman | J25: PvP | K25: Assault | L25: 1m30 | M25: 1200 | N25: Heart Shot | O25: Deals damage to the selected Legion. Damage Type: Artifact Skill Damage (Physical) Damage Factor: 1000 Target has 40% chance to gain Physical DEF Break: Physical DEF -15% for 3s. | P25: Skill Damage Factor: 1000/1200/1400/1700/2000 Probability: 40%/45%/50%/55%/65% | Q25: 1
A26: Bomb Flinger | B26: Marksman Unit ATK | C26: 3 | D26: 28 | E26: Legion ATK | F26: 3 | G26: 18 | H26: epic | I26: Marksman | J26: Peacekeeping | K26: / | L26: 1m30 | M26: 0 | N26: Bomb Away | O26: Deals damage to the selected Legion (Darklings, Dark Creatures, and Behemoths only). Damage Type: Artifact Skill Damage (Physical) Damage Factor: 1200 Damaged targets have a 40% chance to be Stunned: cannot move or act for 2s. | P26: Skill Damage Factor: 1200/1500/1800/2100/2400 Probability: 40%/50%/60%/70%/80% | Q26: 1
A27: Enchiridion of Advanced Incantations | B27: Magic Unit ATK | C27: 3 | D27: 28 | E27: Legion ATK | F27: 3 | G27: 18 | H27: epic | I27: Magic | J27: Peacekeeping | K27: / | L27: 1m30 | M27: 0 | N27: Fireburst | O27: Deals damage to the selected Legion (Darklings, Dark Creatures, and Behemoths only). Damage Type: Artifact Skill Damage (Magic) Damage Factor:1400 | P27: Skill Damage Factor: 1400/1700/2000/2400/2800 | Q27: 1
... A69: Lunaris | B69: Cavalry Unit ATK | C69: 5 | D69: 40 | E69: Legion ATK | F69: 4 | G69: 22 | H69: legendary | I69: Cavalry | J69: PvP | K69: Assault | L69: 1m30 | M69: 600 | N69: Moon's Judgment | O69: Deals diffused damage to up to 3 enemy Legions in a designated cone. Grants the Legion Rampage and Resistance for 10s. Rampage: Damage dealt +7% Resistance: Damage taken -5% Damage Type: Physical Damage Factor: 2200 Additional Effect Legion gains Haste while Camouflaged, and gains Synergy when the Camouflaged status is removed. Haste: March Speed +20% Synergy: Hero Skill damage +10% for 15s. | P69: Skill Damage Factor: 2200/2750/3300/3850/4400 Damage deault bonus: 7%/9%/11%/13%/15% Damage taken reduction: 5%/6%/7%/8%/10% March Speed bonus: 20%/25%/30%/35%/40% Hero Skill damage deault bonus: 10%/12%/14%/17%20% | Q69: 4
A70: Serpent's Edge | B70: Infantry Unit ATK | C70: 5 | D70: 40 | E70: Legion DEF | F70: 4 | G70: 22 | H70: legendary | I70: Infantry | J70: PvP | K70: Tank | L70: 1m30 | M70: 400 | N70: Bloodbite | O70: For the next 20s, the Legion gains 30% HP, and deals diffused Physical damage to up to 3 nearby enemy Legions every 3s (Damage Factor 400). Targets gain Slow: March Speed -10% for 3s. Additional Effect When gaining an HP buff via a Hero Skill, the Legion gains 10% ATK and DEF for 5s (max 5 stacks). | Q70: 4

Sheet Research
A1: No motivation atm

Sheet Main quests
A1: Same

Sheet Hero Token Cost
A1: # of upgrade | B1: Legendary | C1: Total Leg | D1: Epic | E1: Rare | F1: 1/1/1/1 | G1: 4 Upgrades per Skill
A2: 1 | B2: 10 | C2: =sum(B$2:B2) -> 10 | D2: 10 | E2: 10
A3: 2 | B3: 10 | C3: =sum(B$2:B3) -> 20 | D3: 10 | E3: 10
A4: 3 | B4: 15 | C4: =sum(B$2:B4) -> 35 | D4: 10 | E4: 10
A5: 4 | B5: 15 | C5: =sum(B$2:B5) -> 50 | D5: 20 | E5: 10 | F5: 5/1/1/1
A6: 5 | B6: 30 | C6: =sum(B$2:B6) -> 80 | D6: 20 | E6: 10
A7: 6 | B7: 30 | C7: =sum(B$2:B7) -> 110 | D7: 20 | E7: 20
A8: 7 | B8: 40 | C8: =sum(B$2:B8) -> 150 | D8: 20 | E8: 20
A9: 8 | B9: 40 | C9: =sum(B$2:B9) -> 190 | D9: 30 | E9: 20 | F9: 5/5/1/1
A10: 9 | B10: 45 | C10: =sum(B$2:B10) -> 235 | D10: 30 | E10: 20
A11: 10 | B11: 45 | C11: =sum(B$2:B11) -> 280 | D11: 30 | E11: 20
A12: 11 | B12: 50 | C12: =sum(B$2:B12) -> 330 | D12: 30 | E12: 30
A13: 12 | B13: 50 | C13: =sum(B$2:B13) -> 380 | D13: 40 | E13: 30 | F13: 5/5/5/1
A14: 13 | B14: 75 | C14: =sum(B$2:B14) -> 455 | D14: 40 | E14: 30
A15: 14 | B15: 75 | C15: =sum(B$2:B15) -> 530 | D15: 40 | E15: 30
A16: 15 | B16: 80 | C16: =sum(B$2:B16) -> 610 | D16: 40 | E16: 30
A17: 16 | B17: 80 | C17: =sum(B$2:B17) -> 690 | D17: 50 | E17: 40 | F17: 5/5/5/5
A18: Total | B18: =sum(B2:B17) -> 690 | D18: =sum(D2:D17) -> 440 | E18: =sum(E2:E17) -> 340
A21: 235+
A23: 5 | B23: 4364 | D23: =A23*B23 -> 21820
A24: 10 | B24: 6777 | D24: =A24*B24 -> 67770
A25: 50 | B25: 1774 | D25: =A25*B25 -> 88700
A26: 100 | B26: 521 | D26: =A26*B26 -> 52100
A27: 200 | B27: 165 | D27: =A27*B27 -> 33000
A28: 500 | B28: 153 | D28: =A28*B28 -> 76500
A29: 1000 | B29: 102 | D29: =A29*B29 -> 102000
D30: =SUM(D23:D29) -> 441890
A34: 5 | B34: 2104 | C34: =A34*B34 -> 10520 | H34: Damage: | I34: Stats: | K34: Inf: 15 CA
A35: 10 | B35: 5763 | C35: =A35*B35 -> 57630 | H35: 1000 x3 (Diffused) | I35: 10 ATK | K35: Cav: 6 DMG Flat
A36: 50 | B36: 1571 | C36: =A36*B36 -> 78550 | H36: 30 Rage | I36: 20 March Speed | K36: MM: 20 NA DMG
A37: 100 | B37: 449 | C37: =A37*B37 -> 44900 | I37: 20 DEF (merge with ATK Resistance) | K37: Mage: 10 DMG Res
A38: 200 | B38: 155 | C38: =A38*B38 -> 31000
A39: 500 | B39: 134 | C39: =A39*B39 -> 67000 | H39: 300 Damage every 15s
A40: 1000 | B40: 92 | C40: =A40*B40 -> 92000
C41: =SUM(C34:C40) -> 381600
H42: Daily | I42: 1200 | J42: 3.49 | K42: 2 | L42: =I42*K42 -> 2400 | M42: =J42*K42 -> 6.98
A43: 1000 | B43: 305 | C43: =A43*B43 -> 305000 | H43: Monthly 1 | I43: 750 | J43: 3.49 | K43: 2 | L43: =I43*K43 -> 1500 | M43: =J43*K43 -> 6.98
A44: 5000 | B44: 31 | C44: =A44*B44 -> 155000 | H44: Monthly 2 | I44: 1500 | J44: 5.99 | K44: 1 | L44: =I44*K44 -> 1500 | M44: =J44*K44 -> 5.99
A45: 20000 | B45: 63 | C45: =A45*B45 -> 1260000
A46: 50000 | B46: 34 | C46: =A46*B46 -> 1700000
C47: =sum(C43:C46) -> 3420000 | L47: =SUM(L42:L46) -> 5400 | M47: =SUM(M42:M46) -> 19.95

Sheet Talent Tree
A1: ID | B1: Tree | C1: NodeID | D1: Requirement
A2: -3.1 | B2: Foundation Talents | C2: 1 | E2: =VLOOKUP(C2,'Talent Node'!A:E,2,FALSE) -> Overall Attack
A3: -2.2 | B3: Foundation Talents | C3: 2 | E3: =VLOOKUP(C3,'Talent Node'!A:E,2,FALSE) -> Overall Speed
A4: -2.1 | B4: Foundation Talents | C4: 3 | E4: =VLOOKUP(C4,'Talent Node'!A:E,2,FALSE) -> Overall Defense
A5: -1.3 | B5: Foundation Talents | C5: 5 | E5: =VLOOKUP(C5,'Talent Node'!A:E,2,FALSE) -> Logistics Master
A6: -1.2 | B6: Foundation Talents | C6: 4 | E6: =VLOOKUP(C6,'Talent Node'!A:E,2,FALSE) -> Overall Health
A7: -1.1 | B7: Foundation Talents | C7: 27 | E7: =VLOOKUP(C7,'Talent Node'!A:E,2,FALSE) -> Bane of Darkness
A8: 1.1 | B8: Marksman | C8: 13 | E8: =VLOOKUP(C8,'Talent Node'!A:E,2,FALSE) -> Marksman ATK
A9: 2.1 | B9: Marksman | C9: 15 | E9: =VLOOKUP(C9,'Talent Node'!A:E,2,FALSE) -> Marksman Speed
A10: 2.2 | B10: Marksman | C10: 14 | E10: =VLOOKUP(C10,'Talent Node'!A:E,2,FALSE) -> Fully Loaded
A11: 2.3 | B11: Marksman | C11: 11 | E11: =VLOOKUP(C11,'Talent Node'!A:E,2,FALSE) -> Head Held High
A12: 3.1 | B12: Marksman | C12: 18 | E12: =VLOOKUP(C12,'Talent Node'!A:E,2,FALSE) -> Alert
A13: 3.2 | B13: Marksman | C13: 17 | E13: =VLOOKUP(C13,'Talent Node'!A:E,2,FALSE) -> Steady Shot
A14: 3.3 | B14: Marksman | C14: 16 | E14: =VLOOKUP(C14,'Talent Node'!A:E,2,FALSE) -> Intimidation
A15: 4.1 | B15: Marksman | C15: 20 | E15: =VLOOKUP(C15,'Talent Node'!A:E,2,FALSE) -> Shower of Blows
A16: 4.2 | B16: Marksman | C16: 19 | E16: =VLOOKUP(C16,'Talent Node'!A:E,2,FALSE) -> Bullseye
A17: 5.1 | B17: Marksman | C17: 22 | E17: =VLOOKUP(C17,'Talent Node'!A:E,2,FALSE) -> Marksman HP
A18: 5.2 | B18: Marksman | C18: 23 | E18: =VLOOKUP(C18,'Talent Node'!A:E,2,FALSE) -> Magic Countertactics
A19: 5.3 | B19: Marksman | C19: 21 | E19: =VLOOKUP(C19,'Talent Node'!A:E,2,FALSE) -> Egoism
A20: 6.1 | B20: Marksman | C20: 26 | D20: 5.1 | E20: =VLOOKUP(C20,'Talent Node'!A:E,2,FALSE) -> Delight
A21: 6.2 | B21: Marksman | C21: 25 | E21: =VLOOKUP(C21,'Talent Node'!A:E,2,FALSE) -> Binding Snare
A22: 6.3 | B22: Marksman | C22: 24 | E22: =VLOOKUP(C22,'Talent Node'!A:E,2,FALSE) -> Callousness
A23: 7.1 | B23: Marksman | C23: 35 | E23: =VLOOKUP(C23,'Talent Node'!A:E,2,FALSE) -> Last Word
A24: 7.2 | B24: Marksman | C24: 56 | E24: =VLOOKUP(C24,'Talent Node'!A:E,2,FALSE) -> Radical
A25: 7.3 | B25: Marksman | C25: 57 | E25: =VLOOKUP(C25,'Talent Node'!A:E,2,FALSE) -> Harvest
A26: 8.1 | B26: Marksman | C26: 29 | E26: =VLOOKUP(C26,'Talent Node'!A:E,2,FALSE) -> Pursuit
A27: 8.2 | B27: Marksman | C27: 28 | E27: =VLOOKUP(C27,'Talent Node'!A:E,2,FALSE) -> Burst Shot
A28: 1.1 | B28: Rally | C28: 9 | E28: =VLOOKUP(C28,'Talent Node'!A:E,2,FALSE) -> Overall Health
A29: 2.1 | B29: Rally | C29: 8 | E29: =VLOOKUP(C29,'Talent Node'!A:E,2,FALSE) -> Overall Defense
A30: 2.2 | B30: Rally | C30: 6 | E30: =VLOOKUP(C30,'Talent Node'!A:E,2,FALSE) -> Overall Attack
A31: 2.3 | B31: Rally | C31: 7 | E31: =VLOOKUP(C31,'Talent Node'!A:E,2,FALSE) -> Overall Speed
A32: 3.1 | B32: Rally | C32: 247 | E32: =VLOOKUP(C32,'Talent Node'!A:E,2,FALSE) -> Pincer Attack
... A43: 7.1 | B43: Rally | C43: 41 | E43: =VLOOKUP(C43,'Talent Node'!A:E,2,FALSE) -> Frontline Support
A44: 7.2 | B44: Rally | C44: 40 | D44: 6.2 | E44: =VLOOKUP(C44,'Talent Node'!A:E,2,FALSE) -> Plan of Attack
A45: 7.3 | B45: Rally | C45: 252 | E45: =VLOOKUP(C45,'Talent Node'!A:E,2,FALSE) -> Armored Assault
A46: 8.1 | B46: Rally | C46: 43 | E46: =VLOOKUP(C46,'Talent Node'!A:E,2,FALSE) -> Reversal of Fortune
A47: 8.2 | B47: Rally | C47: 42 | E47: =VLOOKUP(C47,'Talent Node'!A:E,2,FALSE) -> Trailblazer
A48: 0 | B48: Precision | C48: 12 | E48: =VLOOKUP(C48,'Talent Node'!A:E,2,FALSE) -> Arrow of Precision
A49: 1.1 | B49: Precision | C49: 6 | E49: =VLOOKUP(C49,'Talent Node'!A:E,2,FALSE) -> Overall Attack
A50: 2.1 | B50: Precision | C50: 7 | E50: =VLOOKUP(C50,'Talent Node'!A:E,2,FALSE) -> Overall Speed
A51: 2.2 | B51: Precision | C51: 31 | E51: =VLOOKUP(C51,'Talent Node'!A:E,2,FALSE) -> Adrenaline Rush
A52: 2.3 | B52: Precision | C52: 21 | E52: =VLOOKUP(C52,'Talent Node'!A:E,2,FALSE) -> Egoism
A53: 3.1 | B53: Precision | C53: 35 | E53: =VLOOKUP(C53,'Talent Node'!A:E,2,FALSE) -> Last Word
A54: 3.2 | B54: Precision | C54: 45 | E54: =VLOOKUP(C54,'Talent Node'!A:E,2,FALSE) -> Strengthened Weaponry
A55: 3.3 | B55: Precision | C55: 44 | E55: =VLOOKUP(C55,'Talent Node'!A:E,2,FALSE) -> All-Conquering
A56: 4.1 | B56: Precision | C56: 58 | E56: =VLOOKUP(C56,'Talent Node'!A:E,2,FALSE) -> Invincible
... A63: 6.3 | B63: Precision | C63: 49 | E63: =VLOOKUP(C63,'Talent Node'!A:E,2,FALSE) -> Suppression
A64: 7.1 | B64: Precision | C64: 53 | D64: 6.1 | E64: =VLOOKUP(C64,'Talent Node'!A:E,2,FALSE) -> Unstoppable
A65: 7.2 | B65: Precision | C65: 52 | D65: 6.2 | E65: =VLOOKUP(C65,'Talent Node'!A:E,2,FALSE) -> Force of Will
A66: 7.3 | B66: Precision | C66: 51 | E66: =VLOOKUP(C66,'Talent Node'!A:E,2,FALSE) -> Dedication
A67: 8.1 | B67: Precision | C67: 55 | E67: =VLOOKUP(C67,'Talent Node'!A:E,2,FALSE) -> Mark of War
A68: 8.2 | B68: Precision | C68: 54 | E68: =VLOOKUP(C68,'Talent Node'!A:E,2,FALSE) -> Mighty Slash
A69: 1.1 | B69: Magic | C69: 100 | E69: =VLOOKUP(C69,'Talent Node'!A:E,2,FALSE) -> Magic HP
A70: 2.1 | B70: Magic | C70: 61 | E70: =VLOOKUP(C70,'Talent Node'!A:E,2,FALSE) -> Magic Speed
A71: 2.2 | B71: Magic | C71: 60 | E71: =VLOOKUP(C71,'Talent Node'!A:E,2,FALSE) -> Foresight
A72: 2.3 | B72: Magic | C72: 14 | E72: =VLOOKUP(C72,'Talent Node'!A:E,2,FALSE) -> Fully Loaded
A73: 3.1 | B73: Magic | C73: 62 | E73: =VLOOKUP(C73,'Talent Node'!A:E,2,FALSE) -> Magic ATK
A74: 3.2 | B74: Magic | C74: 16 | E74: =VLOOKUP(C74,'Talent Node'!A:E,2,FALSE) -> Intimidation
A75: 3.3 | B75: Magic | C75: 44 | E75: =VLOOKUP(C75,'Talent Node'!A:E,2,FALSE) -> All-Conquering
A76: 4.1 | B76: Magic | C76: 63 | E76: =VLOOKUP(C76,'Talent Node'!A:E,2,FALSE) -> Magic Maelstrom
A77: 4.2 | B77: Magic | C77: 64 | E77: =VLOOKUP(C77,'Talent Node'!A:E,2,FALSE) -> Energy Boost
... A80: 5.3 | B80: Magic | C80: 65 | E80: =VLOOKUP(C80,'Talent Node'!A:E,2,FALSE) -> Orb of Protection
A81: 6.1 | B81: Magic | C81: 69 | D81: 5.1 | E81: =VLOOKUP(C81,'Talent Node'!A:E,2,FALSE) -> Wither
A82: 6.2 | B82: Magic | C82: 68 | E82: =VLOOKUP(C82,'Talent Node'!A:E,2,FALSE) -> Chant
A83: 6.3 | B83: Magic | C83: 67 | E83: =VLOOKUP(C83,'Talent Node'!A:E,2,FALSE) -> Shelter of Compassion
A84: 7.1 | B84: Magic | C84: 72 | E84: =VLOOKUP(C84,'Talent Node'!A:E,2,FALSE) -> Bolt from the Blue
A85: 7.2 | B85: Magic | C85: 71 | E85: =VLOOKUP(C85,'Talent Node'!A:E,2,FALSE) -> Insult to Injury
A86: 7.3 | B86: Magic | C86: 70 | E86: =VLOOKUP(C86,'Talent Node'!A:E,2,FALSE) -> Cry Havoc
A87: 8.1 | B87: Magic | C87: 74 | E87: =VLOOKUP(C87,'Talent Node'!A:E,2,FALSE) -> Elemental Boost
A88: 8.2 | B88: Magic | C88: 73 | E88: =VLOOKUP(C88,'Talent Node'!A:E,2,FALSE) -> Iconoclasm
A89: 1.1 | B89: Peacekeeping | C89: 6 | E89: =VLOOKUP(C89,'Talent Node'!A:E,2,FALSE) -> Overall Attack
A90: 2.1 | B90: Peacekeeping | C90: 5 | E90: =VLOOKUP(C90,'Talent Node'!A:E,2,FALSE) -> Logistics Master
A91: 2.2 | B91: Peacekeeping | C91: 75 | E91: =VLOOKUP(C91,'Talent Node'!A:E,2,FALSE) -> Bane of Darkness
A92: 2.3 | B92: Peacekeeping | C92: 7 | E92: =VLOOKUP(C92,'Talent Node'!A:E,2,FALSE) -> Overall Speed
A93: 3.1 | B93: Peacekeeping | C93: 78 | E93: =VLOOKUP(C93,'Talent Node'!A:E,2,FALSE) -> Divine Strategy
... A126: 7.2 | B126: Skills | C126: 96 | E126: =VLOOKUP(C126,'Talent Node'!A:E,2,FALSE) -> Steady Hands
A127: 7.3 | B127: Skills | C127: 97 | D127: 6.3 | E127: =VLOOKUP(C127,'Talent Node'!A:E,2,FALSE) -> Raging Tide
A128: 8.1 | B128: Skills | C128: 98 | E128: =VLOOKUP(C128,'Talent Node'!A:E,2,FALSE) -> Caged Animal
A129: 8.2 | B129: Skills | C129: 99 | E129: =VLOOKUP(C129,'Talent Node'!A:E,2,FALSE) -> Thirst for Blood
A130: 1.1 | B130: Cavalry | C130: 151 | E130: =VLOOKUP(C130,'Talent Node'!A:E,2,FALSE) -> Cavalry Speed
A131: 2.1 | B131: Cavalry | C131: 21 | E131: =VLOOKUP(C131,'Talent Node'!A:E,2,FALSE) -> Egoism
A132: 2.2 | B132: Cavalry | C132: 152 | E132: =VLOOKUP(C132,'Talent Node'!A:E,2,FALSE) -> Cavalry ATK
A133: 2.3 | B133: Cavalry | C133: 31 | E133: =VLOOKUP(C133,'Talent Node'!A:E,2,FALSE) -> Adrenaline Rush
A134: 3.1 | B134: Cavalry | C134: 44 | E134: =VLOOKUP(C134,'Talent Node'!A:E,2,FALSE) -> All-Conquering
A135: 3.2 | B135: Cavalry | C135: 11 | E135: =VLOOKUP(C135,'Talent Node'!A:E,2,FALSE) -> Head Held High
A136: 3.3 | B136: Cavalry | C136: 16 | E136: =VLOOKUP(C136,'Talent Node'!A:E,2,FALSE) -> Intimidation
A137: 4.1 | B137: Cavalry | C137: 154 | E137: =VLOOKUP(C137,'Talent Node'!A:E,2,FALSE) -> Steady Pace
A138: 4.2 | B138: Cavalry | C138: 153 | E138: =VLOOKUP(C138,'Talent Node'!A:E,2,FALSE) -> Perfect Ferocity
A139: 5.1 | B139: Cavalry | C139: 88 | E139: =VLOOKUP(C139,'Talent Node'!A:E,2,FALSE) -> Swift Analysis
... A145: 7.1 | B145: Cavalry | C145: 160 | E145: =VLOOKUP(C145,'Talent Node'!A:E,2,FALSE) -> Triumphant Return
A146: 7.2 | B146: Cavalry | C146: 161 | D146: 6.2 | E146: =VLOOKUP(C146,'Talent Node'!A:E,2,FALSE) -> Entangle
A147: 7.3 | B147: Cavalry | C147: 162 | E147: =VLOOKUP(C147,'Talent Node'!A:E,2,FALSE) -> Pitched Battle
A148: 8.1 | B148: Cavalry | C148: 163 | E148: =VLOOKUP(C148,'Talent Node'!A:E,2,FALSE) -> Inescapable
A149: 8.2 | B149: Cavalry | C149: 164 | E149: =VLOOKUP(C149,'Talent Node'!A:E,2,FALSE) -> Blood Mark
A150: 1.1 | B150: PvP | C150: 6 | E150: =VLOOKUP(C150,'Talent Node'!A:E,2,FALSE) -> Overall Attack
A151: 2.1 | B151: PvP | C151: 165 | E151: =VLOOKUP(C151,'Talent Node'!A:E,2,FALSE) -> Rivalry
A152: 2.2 | B152: PvP | C152: 7 | E152: =VLOOKUP(C152,'Talent Node'!A:E,2,FALSE) -> Overall Speed
A153: 2.3 | B153: PvP | C153: 8 | E153: =VLOOKUP(C153,'Talent Node'!A:E,2,FALSE) -> Overall Defense
A154: 3.1 | B154: PvP | C154: 11 | E154: =VLOOKUP(C154,'Talent Node'!A:E,2,FALSE) -> Head Held High
A155: 3.2 | B155: PvP | C155: 166 | E155: =VLOOKUP(C155,'Talent Node'!A:E,2,FALSE) -> Fury Flame
...

Sheet Talent Node
A1: ID | B1: Name | C1: Max Rank | D1: Description | E1: Node Type | F1: Image | G1: Value 1 | H1: Value 2 | I1: Value 3 | J1: Value 4 | K1: Value 5 | L1: Bonus
A2: 1 | B2: Overall Attack | C2: 3 | D2: Increases the ATK of your Legion's units by {value}%. | E2: node | F2: attack | G2: 0.4 | H2: 0.8 | I2: 1.2 | L2: STATS_ATK
A3: 2 | B3: Overall Speed | C3: 3 | D3: Increases the March Speed of your Legion's unit by {value}%. | E3: node | F3: speed | G3: 2 | H3: 4 | I3: 6 | L3: STATS_MS
A4: 3 | B4: Overall Defense | C4: 3 | D4: Increases the DEF of your Legion's unit by {value}%. | E4: node | F4: defense | G4: 0.4 | H4: 0.8 | I4: 1.2 | L4: STATS_DEF
A5: 4 | B5: Overall Health | C5: 3 | D5: Increases the HP of your Legion's unit by {value}%. | E5: node | F5: hp | G5: 0.4 | H5: 0.8 | I5: 1.2 | L5: STATS_HP
A6: 5 | B6: Logistics Master | C6: 3 | D6: Increases your Legion's Gather Speed by {value}%. | E6: node | F6: gather | G6: 3 | H6: 6 | I6: 9 | L6: GATHERINGSTATS_GATHER
A7: 6 | B7: Overall Attack | C7: 5 | D7: Increases the ATK of your Legion's units by {value}%. | E7: node | F7: attack | G7: 0.4 | H7: 0.8 | I7: 1.2 | J7: 1.6 | K7: 2 | L7: STATS_ATK
A8: 7 | B8: Overall Speed | C8: 5 | D8: Increases the March Speed of your Legion's unit by {value}%. | E8: node | F8: speed | G8: 2 | H8: 4 | I8: 6 | J8: 8 | K8: 10 | L8: STATS_MS
A9: 8 | B9: Overall Defense | C9: 5 | D9: Increases the DEF of your Legion's unit by {value}%. | E9: node | F9: defense | G9: 0.4 | H9: 0.8 | I9: 1.2 | J9: 1.6 | K9: 2 | L9: STATS_DEF
A10: 9 | B10: Overall Health | C10: 5 | D10: Increases the HP of your Legion's unit by {value}%. | E10: node | F10: hp | G10: 0.4 | H10: 0.8 | I10: 1.2 | J10: 1.6 | K10: 2 | L10: STATS_HP | O10: (archer)
A11: 10 | B11: Logistics Master | C11: 5 | D11: Increases your Legion's Gather Speed by {value}%. | E11: node | F11: gather | G11: 3 | H11: 6 | I11: 9 | J11: 12 | K11: 15 | L11: GATHERINGSTATS_GATHER | O11: (mage)
A12: 11 | B12: Head Held High | C12: 5 | D12: Launching a normal attack has a 10% chance to grant your Legion {value} Rage. | E12: node | F12: rage | G12: 10 | H12: 20 | I12: 30 | J12: 40 | K12: 50 | L12: NA_RAGE | O12: (cavalry)
A13: 12 | B13: Arrow of Precision | C13: 1 | D13: Your Legion deals 2% more normal attack damage, and ignores 1% of the enemy's DEF while in battle. | E13: main_node | F13: def_break | L13: STATS_ARROW_OF_PRECISION | O13: (infantry)
A14: 13 | B14: Marksman ATK | C14: 5 | D14: Increases the ATK of your Legion's Marksman units by {value}%. | E14: node | F14: attack | G14: 0.5 | H14: 1 | I14: 1.5 | J14: 2 | K14: 2.5 | L14: STATS_ATK(archer)
A15: 14 | B15: Fully Loaded | C15: 5 | D15: Your Legion deals {value}% more normal attack damage when launching ranged attacks. | E15: node | F15: normal_attack | G15: 1 | H15: 2 | I15: 3 | J15: 4 | K15: 5 | L15: STATS_NA | N15: Trigger
A16: 15 | B16: Marksman Speed | C16: 5 | D16: Increases the March Speed of your Legion's Marksman unit by {value}%. | E16: node | F16: speed | G16: 3 | H16: 6 | I16: 9 | J16: 12 | K16: 15 | L16: STATS_MS(archer) | N16: STATS_ | O16: Raw Stats
A17: 16 | B17: Intimidation | C17: 5 | D17: Your Legion deals {value}% more Hero Skill damage. | E17: node | F17: intimidation | G17: 0.8 | H17: 1.6 | I17: 2.4 | J17: 3.2 | K17: 4 | L17: STATS_HS | N17: RS_ | O17: On Rage Skill
A18: 17 | B18: Steady Shot | C18: 5 | D18: Reduces the Attack Range of your Legion's Marksman units by 3, but increases their ATK by {value}%. | E18: node | F18: attack | G18: 3 | H18: 3.5 | I18: 4 | J18: 4.5 | K18: 5 | L18: STATS_STEADY_SHOT | N18: NA_ | O18: On Normal Attack
A19: 18 | B19: Alert | C19: 5 | D19: Your Legion takes {value}% less damage. | E19: node | F19: angel | G19: 0.3 | H19: 0.6 | I19: 0.9 | J19: 1.2 | K19: 1.5 | L19: STATS_RES | N19: BATTLE_ | O19: When in battle, get x every x
A20: 19 | B20: Bullseye | C20: 1 | D20: When your Legion consists entirely of Marksman units, they gain 5 stacks of ATK Increase every 10s while in battle. Each stack increases their ATK by 1%. Each normal attack they launch removes 1 stack. | E20: major_node | F20: bullseye | G20: 1.5 | L20: BATTLE_BULLEYE | N20: ARTIFACT_ | O20: On Artifacts Skill
A21: 20 | B21: Shower of Blows | C21: 1 | D21: When casting Rage Skills, there is a 50% chance that your next Rage Skill will deal 8% more damage. | E21: major_node | F21: intimidation | G21: 4 | L21: RS_SHOWER_OF_BLOWS | N21: OVER_ | O21: Unit Over
A22: 21 | B22: Egoism | C22: 5 | D22: Your Legion takes {value}% less Hero Skill damage. | E22: node | F22: hs_def | G22: 0.8 | H22: 1.6 | I22: 2.4 | J22: 3.2 | K22: 4 | L22: STATS_HS_RES | N22: LOWER_ | O22: Unit Lower
A23: 22 | B23: Marksman HP | C23: 5 | D23: Increases the HP of your Legion's Marksman units by {value}%. | E23: node | F23: hp | G23: 0.5 | H23: 1 | I23: 1.5 | J23: 2 | K23: 2.5 | L23: STATS_HP(archer) | N23: OTHER_ | O23: Like getting chest on gathering node or idk
A24: 23 | B24: Magic Countertactics | C24: 5 | D24: Your Legion's Marksman units deal {value}% more damage to Magic units. | E24: node | F24: magic_counterattack | G24: 1 | H24: 2 | I24: 3 | J24: 4 | K24: 5 | L24: STATS_DAMAGE_TO_MAGIC(archer) | N24: DEFEATING_ | O24: On defeating legion
A25: 24 | B25: Callousness | C25: 5 | D25: When your Legion's Unit Count is below 50%, their ATK increases by {value}%. | E25: node | F25: callousness | G25: 0.5 | H25: 1 | I25: 1.5 | J25: 2 | K25: 2.5 | L25: LOWER_ATK | N25: DEBUFFAPPLIED_ | O25: On debuff applied/inflicts
A26: 25 | B26: Binding Snare | C26: 5 | D26: When your Legion is hit with a normal attack, they have 10% chance to Slow the target Legion, reducing their March Speed by {value}% for 5s. | E26: node | F26: slow_speed | G26: 4 | H26: 8 | I26: 12 | J26: 16 | K26: 20 | L26: HIT_BINDING_SNARE | N26: DEBUFFRECEIVED_ | O26: On debuff received
A27: 26 | B27: Delight | C27: 5 | D27: Increases Rage Accumulation Speed by {value}% when your Legion's Unit Count is over 50%. | E27: node | F27: rage | G27: 5 | H27: 6 | I27: 9 | J27: 12 | K27: 15 | L27: OVER_RAGE | N27: HEALING_ | O27: On shield or healing received
A28: 27 | B28: Bane of Darkness | C28: 3 | D28: Your Legion deals {value}% more Peacekeeping damage. | E28: node | F28: peacekeeping | G28: 1 | H28: 2 | I28: 3 | L28: PEACEKEEPING_PK_DMG | N28: HIT_ | O28: When hit by Normal Attack
A29: 28 | B29: Burst Shot | C29: 1 | D29: When your Marksman Legion launches a normal attack, they deal additional damage. Damage Type: Physical Damage Factor: 150 This effect can be triggered once every 10s. | E29: major_node | F29: furious | L29: NA_BURST_SHOT | N29: UNIT_ | O29: Legion Size
A30: 29 | B30: Pursuit | C30: 1 | D30: When your Legion consists entirely of Marksman units, they inflict Fragility when casting Rage Skills, increasing normal attack damage taken by 10% for 5s. This effect can be triggered once every 10s. | E30: major_node | F30: def_break | L30: RS_PURSUIT | N30: DMG_ | O30: Damage
A31: 30 | B31: Arson | C31: 5 | D31: When your Legion defeats an enemy Garrisoned Army, the time the City or Stronghold burns for is increased by {value}%. | E31: node | F31: arson | G31: 4 | H31: 8 | I31: 12 | J31: 16 | K31: 20 | L31: OTHER_ARSON | N31: START_ | O31: At start of battle
A32: 31 | B32: Adrenaline Rush | C32: 5 | D32: Your Legion deal {value}% more normal attack damage. | E32: node | F32: normal_attack | G32: 0.8 | H32: 1.6 | I32: 2.4 | J32: 3.2 | K32: 4 | L32: STATS_NA | N32: DEFPEN_ | O32: Defense Penetration
A33: 32 | B33: Watch This | C33: 5 | D33: Increases damage dealt to Watch Towers by {value}%. | E33: node | F33: watch | G33: 5 | H33: 10 | I33: 15 | J33: 20 | K33: 25 | L33: OTHER_WATCH_THIS | N33: HPPEN_ | O33: HP Bypass
A34: 33 | B34: Fair Offense | C34: 1 | D34: While serving as Rally Captain, you can force the enemy Rallied Army or Garrisoned Army into a Fair Fight. In a Fair Fight, all Unit Skills are disabled, and the attributes of Infantry, Cavalry, Marksman, and Magic units of the same level will be adjusted to the same values. | E34: major_node | F34: trophy | L34: RALLY_FAIR_OFFENSE | N34: HSHIT_ | O34: When hit by Rage Skill
A35: 34 | B35: Landslide | C35: 1 | D35: When your Legion's Unit Count is over 50%, units deal 3% more damage. | E35: major_node | F35: landslide | L35: OVER_LANDSLIDE
A36: 35 | B36: Last Word | C36: 5 | D36: Your Legion deals {value}% more counterattack damage. | E36: node | F36: counterattack | G36: 0.8 | H36: 1.6 | I36: 2.4 | J36: 3.2 | K36: 4 | L36: STATS_CA
A37: 36 | B37: Steel Monsoon | C37: 5 | D37: Increases March Speed by {value}% for 10s when your Rallied Army leaves a building after launching a Rally. | E37: node | F37: haste | G37: 8 | H37: 16 | I37: 24 | J37: 32 | K37: 40 | L37: RALLY_STEEL_MONSOON
A38: 37 | B38: Frustration | C38: 5 | D38: When your Legion launches a normal attack, they have a 10% chance to reduce the target's healing and shield received by {value}% for 5s. This effect can be triggered once every 5s. | E38: node | F38: blessing | G38: 1 | H38: 2 | I38: 3 | J38: 4 | K38: 5 | L38: NA_FRUSTRATION
A39: 38 | B39: Flank Protection | C39: 5 | D39: Your Legion takes {value}% less bonus damage from being Surrounded. | E39: node | F39: arson | G39: 15 | H39: 30 | I39: 45 | J39: 60 | K39: 75 | L39: STATS_FLANK_PROTECTION
A40: 39 | B40: War Banner | C40: 5 | D40: Increases maximum Legion Capacity by {value}. | E40: node | F40: arson | G40: 300 | H40: 600 | I40: 900 | J40: 1200 | K40: 1500 | L40: STATS_UNIT
A41: 40 | B41: Plan of Attack | C41: 5 | D41: Increases ATK by {value}% and reduces Hero Skill damage taken by {value*2}% when your Legion is besieging a City or Stronghold. | E41: node | F41: hs_def | G41: 0.4 | H41: 0.8 | I41: 1.2 | J41: 1.6 | K41: 2 | L41: OTHER_PLAN_OF_ATTACK
A42: 41 | B42: Frontline Support | C42: 5 | D42: Reduces dead units in your Legion by {value}% when besieging a city (they will be severely wounded instead). | E42: node | F42: support | G42: 1 | H42: 2 | I42: 3 | J42: 4 | K42: 5 | L42: OTHER_FRONTLINE_SUPPORT
A43: 42 | B43: Trailblazer | C43: 1 | D43: Grants Rampage when your Legion enters battle, increasing damage dealt by 5% for 10s. | E43: major_node | F43: trailblazer | L43: START_TRAILBLAZER
A44: 43 | B44: Reversal of Fortune | C44: 1 | D44: Increases the HP of your Legion by 1% every 10s to a maximum of 3% while in battle. | E44: major_node | F44: hp | L44: BATTLE_REVERSAL_OF_FORTUNE
A45: 44 | B45: All-Conquering | C45: 5 | D45: Your Legion takes {value}% less normal attack damage. | E45: node | F45: na_def | G45: 0.8 | H45: 1.6 | I45: 2.4 | J45: 3.2 | K45: 4 | L45: STATS_RES_NA
A46: 45 | B46: Strengthened Weaponry | C46: 5 | D46: Your Legion deals 1% less Hero Skill damage, but their ATK is increased by {value}%. | E46: node | F46: attack | G46: 1 | H46: 1.3 | I46: 1.7 | J46: 2.1 | K46: 2.5 | L46: STATS_STRENGTHENED_WEAPONRY
A47: 46 | B47: Irrepressible | C47: 5 | D47: In battle, your Legion ignores {value}% of the enemy's DEF. | E47: node | F47: def_break | G47: 0.4 | H47: 0.8 | I47: 1.2 | J47: 1.6 | K47: 2 | L47: STATS_DEFPEN
A48: 47 | B48: Cool Under Pressure | C48: 5 | D48: Your Legion deals {value}% more normal attack damage when their Unit Count is above 50%. | E48: node | F48: normal_attack | G48: 2 | H48: 4 | I48: 6 | J48: 8 | K48: 10 | L48: OVER_NA
A49: 48 | B49: Initial Intuition | C49: 5 | D49: {value}% chance to remove a debuff effect when your Legion launches a normal attack. | E49: node | F49: intuition | G49: 2 | H49: 4 | I49: 6 | J49: 8 | K49: 10 | L49: NA_INITIAL_INTUITION
A50: 49 | B50: Suppression | C50: 5 | D50: 25% to inflict Fragility on the target Legion when casting Rage Skills, increasing normal attack damage taken by {value}% for 5s. | E50: node | F50: normal_attack2 | G50: 2 | H50: 4 | I50: 6 | J50: 8 | K50: 10 | L50: RS_SUPPRESSION
A51: 50 | B51: Intrepid | C51: 5 | D51: When your Legion launches a normal attack they have 100% chance to gain Normal Attack Focus, increasing their normal attack Crit Rate by {value}% for 5s. This effect can be triggered once every 8s. | E51: node | F51: bullseye | G51: 1.5 | H51: 3 | I51: 4.5 | J51: 6 | K51: 8 | L51: NA_INTREPID
A52: 51 | B52: Dedication | C52: 5 | D52: Launching a normal attack has a 10% chance to heal your Legion (Healing Factor {value}). | E52: node | F52: crit_damage | G52: 30 | H52: 60 | I52: 90 | J52: 120 | K52: 150 | L52: NA_DEDICATION
A53: 52 | B53: Force of Will | C53: 5 | D53: When casting Rage Skills, your Legion has a 25% chance to gain Onslaught, increasing their normal attack damage by {value}% for 5s. | E53: node | F53: normal_attack | G53: 2 | H53: 4 | I53: 6 | J53: 8 | K53: 10 | L53: RS_FORCE_OF_WILL
A54: 53 | B54: Unstoppable | C54: 5 | D54: Your Legion deals {value}% more normal attack Crit damage. | E54: node | F54: crit_damage | G54: 3 | H54: 6 | I54: 9 | J54: 12 | K54: 15 | L54: STATS_NA_CRIT_DMG
A55: 54 | B55: Mighty Slash | C55: 1 | D55: When launching a normal attack, your Legion has a 15% chance to trigger an additional normal attack. This effect can be triggered once every 20s. | E55: major_node | F55: multiple_arrow | L55: NA_MIGHTY_SLASH
A56: 55 | B56: Mark of War | C56: 1 | D56: Increases the ATK of your Legion by 0.5% every 10s to a maximum of 3%. | E56: major_node | F56: trailblazer | L56: BATTLE_MARK_OF_WAR
A57: 56 | B57: Radical | C57: 5 | D57: Reduces your Legion's DEF by {value}%, but increases their damage dealt by {value*2}%. | E57: node | F57: landslide | G57: 0.3 | H57: 0.6 | I57: 0.9 | J57: 1.2 | K57: 1.5 | L57: STATS_RADICAL
A58: 57 | B58: Harvest | C58: 5 | D58: Every time your Legion defeats an enemy Legion, their ATK increases by {value}%, up to a maximum of {value*2}%. | E58: node | F58: magic_counterattack | G58: 0.5 | H58: 1 | I58: 1.5 | J58: 2 | K58: 2.5 | L58: DEFEATING_HARVEST
A59: 58 | B59: Invincible | C59: 1 | D59: When launching a normal attack, your Legion has a 10% chance to gain Onslaught, increasing their normal attack damage by 8% for 5s. | E59: major_node | F59: normal_attack2 | L59: NA_INVINCIBLE
A60: 59 | B60: Whirlwind | C60: 1 | D60: When launching a normal attack, your Legion has a 10% chance to deal Hero Skill damage (Damage Factor 150). | E60: major_node | F60: cleave | L60: NA_WHIRLWIND
A61: 60 | B61: Foresight | C61: 5 | D61: When casting Rage Skills, your Legion has 25% chance to gain {value} Rage. | E61: node | F61: rage | G61: 15 | H61: 30 | I61: 45 | J61: 60 | K61: 75 | L61: RS_FORESIGHT
A62: 61 | B62: Magic Speed | C62: 5 | D62: Increases the March Speed of your Legion's Magic units by {value}%. | E62: node | F62: speed | G62: 3 | H62: 6 | I62: 9 | J62: 12 | K62: 15 | L62: STATS_MS(magic)
A63: 62 | B63: Magic ATK | C63: 5 | D63: Increases ATK of your Legion's Magic units by {value}%. | E63: node | F63: attack | G63: 0.5 | H63: 1 | I63: 1.5 | J63: 2 | K63: 2.5 | L63: STATS_ATK(magic)
A64: 63 | B64: Magic Maelstrom | C64: 1 | D64: When your Legion consists entirely of Magic units, they gain DEF Penetration before casting Rage Skills, ignoring 10% of the target's DEF for 5s. This effect can be triggered once every 30s. | E64: major_node | F64: def_break | L64: RS_MAGIC_MAELSTROM
A65: 64 | B65: Energy Boost | C65: 1 | D65: 8% chance to add an additional target to Rage Skills that deal damage to multiple targets. | E65: major_node | F65: intuition | L65: RS_ENERGY_BOOST
A66: 65 | B66: Orb of Protection | C66: 5 | D66: When casting Rage Skills, your Legion has a 25% chance to gain a shield (Shield Factor {value}). | E66: node | F66: orb_of_protection | G66: 40 | H66: 80 | I66: 120 | J66: 160 | K66: 200 | L66: RS_ORB_OF_PROTECTION
A67: 66 | B67: Infantry Countertactics | C67: 5 | D67: Your Legion's Magic units deal {value}% more damage to Infantry units. | E67: node | F67: armor_countertactics | G67: 1 | H67: 2 | I67: 3 | J67: 4 | K67: 5 | L67: STATS_DMG_TO_INF(magic)
A68: 67 | B68: Shelter of Compassion | C68: 5 | D68: Increases your Legion's shield granted by {value}% | E68: node | F68: angel | G68: 1 | H68: 2 | I68: 3 | J68: 4 | K68: 5 | L68: STATS_SHIELD
A69: 68 | B69: Chant | C69: 5 | D69: Your Legion takes {value}% more Hero Skill damage, but their ATK is increasing by {value}% | E69: node | F69: chant | G69: 0.5 | H69: 1 | I69: 1.5 | J69: 2 | K69: 2.5 | L69: STATS_CHANT
A70: 69 | B70: Wither | C70: 5 | D70: When your Legion takes Skill damage, they have a 50% chance to inflict Magic DEF Break on the target Legion, reducing their Magic DEF by {value}% for 3s. | E70: node | F70: cursed | G70: 1 | H70: 2 | I70: 3 | J70: 4 | K70: 5 | L70: HSHIT_WITHER
A71: 70 | B71: Cry Havoc | C71: 5 | D71: When target Legion's Unit Count is less than 50%, your Legion deals {value}% more Hero Skill damage. | E71: node | F71: intimidation | G71: 1.5 | H71: 3 | I71: 4.5 | J71: 6 | K71: 7.5 | L71: LOWER_HS
A72: 71 | B72: Insult to Injury | C72: 5 | D72: When your Legion is only composed of Magic units, they deal {value}% more damage through continuous damage effects. | E72: node | F72: fire | G72: 1 | H72: 2 | I72: 3 | J72: 4 | K72: 5 | L72: STATS_DOT(magic)
A73: 72 | B73: Bolt from the Blue | C73: 5 | D73: When casting Rage Skill, your Legion gains Haste, increasing their March Speed by {value}% for 5s. This effect can only be triggered once every 10s. | E73: node | F73: haste | G73: 4 | H73: 8 | I73: 12 | J73: 16 | K73: 20 | L73: RS_BOLT_FROM_THE_BLUE
A74: 73 | B74: Iconoclasm | C74: 1 | D74: When your Legion is composed entirely of magic units, you deal 2% more Hero Skill damage for 10s every time you gain a buff effect, up to 10%. | E74: major_node | F74: cleave | L74: BUFF_ICONOCLASM(magic)
A75: 74 | B75: Elemental Boost | C75: 1 | D75: If your Legion consists entirely of Magic units, they gain Vigor when casting Rage Skills, increasing their HP by 15% for 4s. This effect can only be triggered once every 10s. | E75: major_node | F75: blessing | L75: RS_ELEMENTAL_BOOST(magic)
A76: 75 | B76: Bane of Darkness | C76: 5 | D76: Your Legion deals {value}% more Peacekeeping damage. | E76: node | F76: peacekeeping | G76: 1 | H76: 2 | I76: 3 | J76: 4 | K76: 5 | L76: PEACEKEEPING_PK_DMG
A77: 76 | B77: Weakness Attack | C77: 5 | D77: Your Legion deals {value}% more Peacekeeping normal attack damage. | E77: node | F77: normal_attack | G77: 2 | H77: 4 | I77: 6 | J77: 8 | K77: 10 | L77: PEACEKEEPING_PK_NA
A78: 77 | B78: Fighting Spirit | C78: 5 | D78: Launching a Peacekeeping normal attack has a 10% chance to grant your Legion {value} Rage. | E78: node | F78: rage | G78: 20 | H78: 40 | I78: 60 | J78: 80 | K78: 100 | L78: PEACEKEEPING_FIGHTING_SPIRIT
A79: 78 | B79: Divine Strategy | C79: 5 | D79: Your Legion deals {value}% more Peacekeeping Hero Skill damage. | E79: node | F79: intimidation | G79: 2 | H79: 4 | I79: 6 | J79: 8 | K79: 10 | L79: PEACEKEEPING_PK_HS
A80: 79 | B80: Steadfast Shield | C80: 1 | D80: Your Legion has a 10% chance to gain a shield when Peacekeeping (Shield Factor 400) that absorbs damage for 5s. | E80: major_node | F80: orb_of_protection | L80: PEACEKEEPING_STEADFAST_SHIELD
A81: 80 | B81: Duet | C81: 1 | D81: Your Legion has a 10% chance to deal additional Hero Skill damage when Peacekeeping (Damage Factor 400). This effect can be triggered once every 5s. | E81: major_node | F81: duet | L81: PEACEKEEPING_DUET
A82: 81 | B82: Morale | C82: 5 | D82: Being hit with a normal attack while Peacekeeping has a 10% chance to grant your Legion {value} Rage. | E82: node | F82: rage | G82: 20 | H82: 40 | I82: 60 | J82: 80 | K82: 100 | L82: PEACEKEEPING_MORALE
A83: 82 | B83: Feint | C83: 5 | D83: When your Legion is Peacekeeping, they have a 10% chance to inflict Slow and DEF Break upon the target, reducing their March Speed by {value*5}% and their DEF by {value}% for 3s. | E83: node | F83: feint | G83: 2 | H83: 4 | I83: 6 | J83: 8 | K83: 10 | L83: PEACEKEEPING_FEINT
A84: 83 | B84: Agility | C84: 5 | D84: Your Legion takes {value}% less Peacekeeping Ranged damage. | E84: node | F84: agility | G84: 1.5 | H84: 3 | I84: 4.5 | J84: 6 | K84: 7.5 | L84: PEACEKEEPING_AGILITY
A85: 84 | B85: Prepared | C85: 5 | D85: Your Legion takes {value}% less Peacekeeping damage. | E85: node | F85: angel | G85: 1 | H85: 2 | I85: 3 | J85: 4 | K85: 5 | L85: PEACEKEEPING_PREPARED
A86: 85 | B86: Predestination | C86: 5 | D86: Gain a additional Level 1 Tactics Manual x{value} after Peacekeeping. | E86: node | F86: chant | G86: 1 | H86: 2 | I86: 3 | J86: 4 | K86: 5 | L86: PEACEKEEPING_PREDESTINATION
A87: 86 | B87: War Trophy | C87: 1 | D87: Your Legion gains extra item rewards after Peacekeeping. | E87: major_node | F87: trophy | L87: PEACEKEEPING_WAR_TROPHY
A88: 87 | B88: Sunbather | C88: 1 | D88: When your Legion is Peacekeeping, they are healed every time their Commander casts a Rage Skill (Healing Factor 300). | E88: major_node | F88: vitality | L88: PEACEKEEPING_SUNBATHER
A89: 88 | B89: Swift Analysis | C89: 5 | D89: Your Legion takes {value}% less counterattack damage. | E89: node | F89: reflect | G89: 0.8 | H89: 1.6 | I89: 2.4 | J89: 3.2 | K89: 4 | L89: STATS_CA_RES
A90: 89 | B90: Boiling Blood | C90: 1 | D90: When your Commander casts a Rage Skill, your Legion's Deputy deals 8% more damage the next time they cast a Rage Skill. | E90: major_node | F90: boiling_blood | L90: RS_BOILING_BLOOD
A91: 90 | B91: Spirit of Rage | C91: 1 | D91: Casting Rage Skills grants 20 additional Rage. | E91: major_node | F91: rage | L91: RS_SPIRIT_OF_RAGE
A92: 91 | B92: Detached | C92: 5 | D92: Your Legion deals {value}% less normal attack damage, but {value*2}% more Hero Skill damage. | E92: node | F92: intimidation | G92: 0.8 | H92: 1.6 | I92: 2.4 | J92: 3.2 | K92: 4 | L92: STATS_DETACHED
A93: 92 | B93: Concentration | C93: 5 | D93: When casting Rage Skills, your Legion gains Shelter, increasing their DEF by {value}% for 2s. | E93: node | F93: defense | G93: 0.6 | H93: 1.2 | I93: 1.8 | J93: 2.4 | K93: 3 | L93: RS_CONCENTRATION
A94: 93 | B94: Noble Contract | C94: 5 | D94: Increases all healing received by your Legion by {value}%, and increasing shields received by {value}%. | E94: node | F94: orb_of_protection | G94: 0.5 | H94: 1 | I94: 1.5 | J94: 2 | K94: 2.5 | L94: STATS_NOBLE_CONTRACT
A95: 94 | B95: Focus | C95: 5 | D95: When launching a normal attack, your Legion has a 10% chance to gain Hero Skill Focus, increasing their Hero Skill Crit Rate by {value}% for 5s. | E95: node | F95: focus | G95: 2 | H95: 4 | I95: 6 | J95: 8 | K95: 10 | L95: NA_FOCUS
A96: 95 | B96: Encouraging Dance | C96: 5 | D96: Being hit with a normal attack has a 10% chance to grant your Legion {value} Rage. | E96: node | F96: rage | G96: 10 | H96: 20 | I96: 30 | J96: 40 | K96: 50 | L96: HIT_ENCOURAGING_DANCE
A97: 96 | B97: Steady Hands | C97: 5 | D97: When gaining a buff effect, your Legion has a 20% chance to gain Synergy, increasing their Hero Skill damage dealt by {value} for 5s. This effect can be triggered once every 5s. | E97: node | F97: intimidation | G97: 2 | H97: 4 | I97: 6 | J97: 8 | K97: 10 | L97: BUFFRECEIVED_STEADY_HANDS
A98: 97 | B98: Raging Tide | C98: 5 | D98: Your Legion deals {value}% more Hero Skill Crit Damage | E98: node | F98: raging_tide | G98: 3 | H98: 6 | I98: 9 | J98: 12 | K98: 15 | L98: STATS_HS_CD
A99: 98 | B99: Caged Animal | C99: 1 | D99: Every time your Legion casts a Rage Skill, they deal a 0.5% more Hero Skill damage, up to a maximum of 8%. This effect lasts until battle ends. | E99: major_node | F99: intimidation | L99: RS_CAGED_ANIMAL
A100: 99 | B100: Thirst for Blood | C100: 1 | D100: When casting a Rage Skill, your Legion deals additional Hero Skill damage to the target Legion (Damage Factor 60). | E100: major_node | F100: cleave | L100: RS_THIRST_FOR_BLOOD
...

Sheet Hero
A1: Name | B1: Title | C1: Quality | D1: Category 1 | E1: Category 2 | F1: Category 3 | G1: Season | H1: Flying
A2: Ordo | B2: One-Eyed Veteran | C2: rare | D2: Overall | E2: Engineering | F2: Tank | G2: 1 | H2: FALSE
A3: Chakcha | B3: Gourmet Hunter | C3: rare | D3: Overall | E3: Gather | F3: Skills | G3: 1 | H3: FALSE
A4: Kella | B4: Savvy Trader | C4: rare | D4: Overall | E4: Gather | F4: Support | G4: 1 | H4: FALSE
A5: Pan | B5: Dream Herald | C5: epic | D5: Overall | E5: Gather | F5: Support | G5: 1 | H5: FALSE
A6: Atheus | B6: Auspex | C6: epic | D6: Magic | E6: PvP | F6: Mobility | G6: 1 | H6: TRUE
A7: Waldyr | B7: Ice Mage | C7: epic | D7: Magic | E7: PvP | F7: Skills | G7: 1 | H7: FALSE
A8: Gwanwyn | B8: Arrow of the Wind | C8: epic | D8: Marksman | E8: Peacekeeping | F8: Precision | G8: 1 | H8: FALSE
A9: Kregg | B9: Mad Bomber | C9: epic | D9: Marksman | E9: Engineering | F9: Mobility | G9: 1 | H9: TRUE
A10: Alistair | B10: Royal Court Guard | C10: epic | D10: Cavalry | E10: Rally | F10: Tank | G10: 1 | H10: FALSE
A11: Alwyn | B11: Master of Poisons | C11: epic | D11: Magic | E11: PvP | F11: Control | G11: 1 | H11: FALSE
A12: Bakhar | B12: Unyielding Blade | C12: epic | D12: Infantry | E12: Garrison | F12: Skills | G12: 1 | H12: FALSE
A13: Eliana | B13: Daughter of Dawn | C13: epic | D13: Overall | E13: Peacekeeping | F13: Support | G13: 1 | H13: FALSE
... A52: Lei Kuan | B52: Thunder God | C52: legendary | D52: Infantry | E52: Rally | F52: Tank | G52: 4 | H52: FALSE

Sheet Hero Skills
A1: Hero | B1: Name | C1: Rage Cost | D1: Description | E1: Upgrade | F1: Skill Enhanced | G1: Holistic
A2: Ordo | B2: Unbreakable Barrier | C2: 1000 | D2: Legion gains a shield for 5s that absorbs a massive amount of damage (Shield Factor 400). | E2: Shield Factor 150/200/250/325/400
A3: Ordo | B3: In Full Swing | D3: All Legions: Increases Engineering by 18% when building or destroying buildings in the field. | E3: Engineering bonus 6%/9%/12%/15%/18% | G3: TRUE
A4: Ordo | B4: Clearsighted | D4: All Legions: Increases Gather Speed by 5%, Load Capacity by 5%, and Mana Gather Speed by an extra 10%. | E4: Gather Speed bonus 1%/2%/3%/4%/5% Legion Load Capacity bonus 1%/2%/3%/4%/5% Mana Gather Speed bonus 3%/4%/6%/8%/10% | G4: TRUE
A5: Ordo | B5: Seasoned | D5: Reduces all damage taken by Legion by 10%. This damage reduction is doubled while the Legion is building or destroying Infrastructure or gathering resources. | E5: Damage taken reduction 3%/4%/6%/8%/10%
A6: Bertrand | B6: Entitled Rage | C6: 1000 | D6: Bertrand deals damage to the target Legion and consumes all stacks of Golden Mark, increasing damage dealt by 5% per stack. Damage Type: Magic Damage Factor: 1300 | E6: Skill Damage Factor 700/800/900/1100/1300
A7: Bertrand | B7: Compound Interest | D7: When Legion deals Hero Skill damage, they gains 1 stack of Golden Mark for 5s (max 3 stacks). Each stack of Golden Mark increases Hero Skill damage dealt by 10%. | E7: Hero Skill damage dealt bonus 4%/5%/6%/8%/10%
A8: Bertrand | B8: Magic Circle | D8: Legion Magic units gain 25% Magic ATK and 10% DEF Penetration. | E8: Magic unit Magic ATK bonus 10%/13%/16%/20%/25% Magic unit enemy DEF penetration 4%/5%/6%/8%/10%
A9: Bertrand | B9: Blue Blood | D9: While in the field, Legion gains 15% ATK and DEF if they have not taken normal attack damage for 3s. | E9: ATK and DEF bonus 5%/7%/9%/12%/15%
A10: Bertrand | B10: Noblesse Oblige | D10: Bertrand deals damage to the target Legion and consumes all stacks of Golden Mark, increasing damage dealt by 5% per stack. Damage Type: Magic Damage Factor: 1500 | F10: Entitled Rage
A11: Tohar | B11: Earth Conduit | D11: After launching 3 normal attacks, Tohar channels Rage of the Plateau, dealing damage to the target every second for up to 3s. Damage Type: Magic Damage Factor: 500 Cooldown: 4s If a Hero in Tohar's Legion casts a Rage Skill, the cooldown ands immediatly. | E11: Skill Damage Factor 250/300/350/400/500
A12: Tohar | B12: Defensive Fortifications | D12: When garrisoning Cities or Strongholds, the Garrisoned Army gains 20% ATK. Each time Earth Conduit is cast, it has a 50% chance to hit an extra 3 enemy Legions, dealing diffused damage (Damage Factor 200). | E12: ATK bonus 10%/12%/14%/16%/20%
A13: Tohar | B13: Shamanic Mastery | D13: Legion Magic units deal 30% more Hero skill damage, but deal 5% less normal attack damage. | E13: Magic unit Hero Skill damage dealt bonus 10%/15%/20%/25%/30%
A14: Tohar | B14: Plateau Protection | D14: When channeling Rage of the Plateau, his Legion gains Unyielding and Shelter for 5s. Unyielding: Counterattack damage taken -15% Shelter: DEF +35% | E14: Counterattack damage taken reduction 5%/7%/9%/12%/15% DEF bonus 15%/20%/25%/30%/35%
A15: Tohar | B15: Earth Ritual | D15: After Tohar finishes channeling Rage of the Plateau, his Legion gains Keen: ATK +35% for 5s.
A16: Syndrion | B16: Greenfeather | C16: 1000 | D16: Legion gains Keen and Rapid-Fire, increasing their ATK by 20% and launching and additional normal attack every second for 7s. | E16: Duration 3/4/5/6/7
A17: Syndrion | B17: Soaring Ambition | D17: When besieging a City or Stronghold, Legion gains 10% ATK and ignores 5% of the enemy's DEF. | E17: ATK bonus 4%/5%/6%/8%/10% DEF Penetration 1%/2%/3%/4%/5%
A18: Syndrion | B18: Feather Strike | D18: Legion Marksman units gain 10% normal attack Crit Rate and 15% HP. | E18: Marksman unit normal attack Crit Rate bonus 4%/5%/6%/8%/10% Marksman unit HP bonus 5%/7%/9%/12%/15%
A19: Syndrion | B19: Forest Shadow | D19: When battle begins, Legion gains Rapid-Fire for 3s, launching an extra attack every time they launch a normal attack. 3s after battle begins, Legion gains 20% ATK, lasting until battle ends. | E19: ATK bonus 10%/12%/14%/16%/20% Duration 1/1/2/2/3
A20: Syndrion | B20: Free as the Wind | D20: Every time Syndrion's Legion lands 5 critical hit(s) from normal attacks, they deal additional damage to the target Legion. Damage Type: Physical Damage Factor: 400
A21: Skogul | B21: Bloodsoaked Battle | C21: 1000 | D21: Skogul's Legion gains Vigor and Bloodfury for 6s. Vigor: HP +15% Bloodfury: Legion deals additional diffused counterattack damage every second to all Legions at close range when they launch a normal attack on your Legion | E21: Duration 2/3/4/5/6 HP bonus 5%/7%/9%/12%/15%
A22: Skogul | B22: Unshakeable | D22: Legion Infantry units gain 20% Physical ATK and 10% HP. | E22: Infantry unit Physical ATK bonus 5%/8%/11%/15%/20% HP bonus 4%/5%/6%/8%/10%
A23: Skogul | B23: Guerilla Tactics | D23: While in the field, Legion gains 60% March Speed every time they Berserker Charge and 1% ATK every time they launch a counterattack, up to a maximum of 25%. | E23: Max ATK bonus 10%/13%/16%/20%/25%
A24: Skogul | B24: Tough as Nails | D24: Legion has 10% chance to receive healing when hit with a normal attack (Healing Factor 350). This effect can be triggered once every 5s. | E24: Healing Factor 150/200/250/300/350
A25: Skogul | B25: Glory to Wilderburg! | D25: Legion Infantry units deal 10% more counterattack damage.
A26: Goresh | B26: Wild Blood | C26: 1000 | D26: Goresh's Legion gains Physical Keen and Resistance for 6s. Physical Keen: Physical ATK +50% Resistance: Damage taken -15% | E26: Duration 2/3/4/5/6 Physical ATK bonus 20%/25%/30%/40%/50% Damage taken reduction 5%/7%/9%/12%/15%
A27: Goresh | B27: Steel Skin | D27: Legion Infantry units gain 15% DEF and deal 20% more counterattack damage. | E27: Infantry unit counterattack damage bonus 5%/8%/11%/15%/20% Infantry unit DEF bonus 5%/7%/9%/12%/15%
A28: Goresh | B28: Ruthless | D28: When Legion launches a counterattack, they have a 50% chance to deal additional damage to up to 5 surrounding Legions. Each additional Legion targeted reduces damage taken by 15%. This effect can be triggered up to 2 times per second. Damage Type: Physical Damage Factor: 200 | E28: Skill Damage Factor 50/80/110/150/200
A29: Goresh | B29: Ravaging Army | D29: When besieging a City or Stronghold, Legion gains 20% ATK. If the target Garrison Captain is an Infantry Hero, for every other attacking Legion in the siege, this Hero's Legion gains a 20% chance (up to 60%) to inflict Cower (counterattack damage -50%) for 3s when it launches a normal attack. | E29: ATK bonus 5%/8%/11%/15%/20%
A30: Goresh | B30: Total Domination | D30: Before Awakening Goresh's Legion gains Physical Keen and Resistance for 6s. Physical Keen: Physical ATK +50% Resistance: Damage taken -15% After Awakening Goresh's Legion gains Physical Keen and Resistance for 6s. Physical Keen: Physical ATK +60% Resistance: Damage taken -20% | F30: Wild Blood
A31: Eliana | B31: Benediction of Aurora | C31: 1000 | D31: Grants Eliana's Legion a Divine Shield and deals damage to the target Legion. Shield Factor: 500 Shield Duration: 5s Damage Type: Physical/Magic Damage Factor: 200 | E31: Shield Factor 200/270/350/420/500 Physical Skill Damage Factor 100/120/140/170/200 Magic Skill Damage Factor 100/120/140/170/200
A32: Eliana | B32: Purifying Touch | D32: All Legions: Increases damage dealt when peacekeeping by 7% and XP gained when peacekeeping by 20%. | E32: Damage dealt during Peacekeeping bonus 1%/2%/3%/4%/5%/7%(Awakened) Hero EXP bonus 6%/8%/10%/12%/15%/20%(Awakened) | G32: TRUE
A33: Eliana | B33: Leosa's Brilliance | D33: Legion takes 30% less normal attack damage. | E33: Normal attack damage reduction 10%/15%/20%/25%/30%
A34: Eliana | B34: Holy Heart | D34: When casting Rage Skills, Legion gains Shelter, increasing their DEF by 30% for 5s. | E34: DEF bonus 10%/15%/20%/25%/30%
A35: Eliana | B35: Divine Grace | D35: Grants a Divine Shield to Eliana's Legion, giving them a 70% chance to receive healing when hit with a normal attack (Healing Factor 400). This effect can be triggered once every 3s.
A36: Liliya | B36: Flames of Vengeance | C36: 1000 | D36: Deals diffused damage to the target and 2 nearby Legions, with a 50% chance to inflict Scorch: deals damage every second for 5s. Damage Type: Magic Damage Factor (Targets): 1200 Damage Factor (Scorch): 200 | E36: Skill Damage Factor 600/700/800/1000/1200 Probability 10%/20%/30%/40%/50%
A37: Liliya | B37: Dazzling Inferno | D37: All Legions: Increases damage dealt when peacekeeping by 15%. | E37: Damage dealt during Peacekeeping bonus 4%/6%/8%/10%/12%/15%(Awakened) | G37: TRUE
A38: Liliya | B38: Deep Burn | D38: Legion Magic units gain 20% Magic ATK and 10% HP. | E38: Magic unit Magic ATK bonus 10%/12%/14%/16%/20% Magic unit HP bonus 4%/5%/6%/8%/10%
A39: Liliya | B39: Witchy Wiles | D39: When Liliya's Legion launches a normal attack, 30% chance to Scorch up to 2 surrounding enemy Legions, if the target Legion is Scorched. | E39: Probability 10%/15%/20%/25%/30%
A40: Liliya | B40: Burning Blood | D40: Before Awakening Deals diffused damage to the target and 1 nearby Legions, with a 50% chance to inflict Scorch: deals damage every second for 5s. Damage Type: Magic Damage Factor (Targets): 1200 Damage Factor (Scorch): 200 After Awakening Deals diffused damage to the target and 2 nearby Legions, with a 50% chance to inflict Scorch: deals damage every second for 5s. Damage Type: Magic Damage Factor (Targets): 1200 Damage Factor (Scorch): 200 | F40: Flames of Vengeance
A41: Kella | B41: Roadblock | C41: 1000 | D41: Slows and inflicts Gloom on an enemy Legion, reducing their ATK by 20% and their March Speed by 30% for 4s. | E41: ATK reduction 5%/8%/11%/15%/20% March Speed reduction 6%/12%/18%/24%/30%
A42: Kella | B42: Midas Touch | D42: All Legions: Increases Gather Speed by 5% and Gold Gather Speed by an extra 10%. | E42: Gather Speed bonus 1%/2%/3%/4%/5% Gold Gather Speed bonus 3%/4%/6%/8%/10% | G42: TRUE
A43: Kella | B43: Caravaneer | D43: All Legions: Increases Load Capacity by 10%. | E43: Legion Load Capacity bonus 3%/4%/6%/8%/10% | G43: TRUE
A44: Kella | B44: Tender Care | D44: Reduces all damage taken by Kella’s Legion by 10%and reduces the number of severely wounded units for both her Legion and the enemy’s Legion by 15%, leaving those units lightly wounded instead. | E44: Severely wounded reduction 3%/6%/9%/12%/15%
A45: Chakcha | B45: Hunter’s Instinct | C45: 1000 | D45: Grants Riposte and Passion, increasing counterattack damage by 15% and increasing Rage Accumulation Speed by 15% for 5s. | E45: Counterattack damage bonus 5%/7%/9%/12%/15% Rage Accumulation Speed bonus 5%/7%/9%/12%/15%
A46: Chakcha | B46: Mountain Mover | D46: All Legions: Increases Gather Speed by 5%, Load Capacity by 5%, and Ore Gather Speed by an extra 10%. | E46: Gather Speed bonus 1%/2%/3%/4%/5% Legion Load Capacity bonus 1%/2%/3%/4%/5% Ore Gather Speed bonus 3%/4%/6%/8%/10% | G46: TRUE
A47: Chakcha | B47: Hands-on Experience | D47: Increases Legion DEF by 7%. | E47: DEF bonus 2%/3%/4%/5%/7%
A48: Chakcha | B48: Comfort Food | D48: Increases Legion HP by 7% and automatically heals the Legion’s lightly wounded units after defeating an enemy Legion (Healing Factor 1000). | E48: HP bonus 2%/3%/4%/5%/7% Healing Factor 300/450/600/800/1000
A49: Alistair | B49: Spear of Judgement | C49: 1000 | D49: Deals damage to the target and 2 nearby Legions. Damage Type: Physical Damage Factor: 600 | E49: Skill Damage Factor 200/300/400/500/600
A50: Alistair | B50: Devotion | D50: Alistair’s Legion gains 10% HP and 10% Physical ATK. | E50: HP bonus 4%/5%/6%/8%/10% Physical ATK bonus 4%/5%/6%/8%/10%
A51: Alistair | B51: Hold the Line | D51: 20% chance to increase DEF by 30% for 2s when attacking Cities and Strongholds. This effect can be triggered once every 5s. | E51: DEF bonus 10%/15%/20%/25%/30%
A52: Alistair | B52: Light of Sorland | D52: When the Legion has over 50% units remaining, it has a 20% chance to gain Riposte and Passion when launching normal attacks, increasing Counterattack damage dealt by 30% and Rage Accumulation Speed by 30% for 3s. This effect can be triggered once every 5s. | E52: Counterattack damage bonus 10%/15%/20%/25%/30% Rage Accumulation Speed bonus 10%/15%/20%/25%/30%
A53: Alistair | B53: Chivalric Oath | D53: Legion Cavalry units deal 10% more normal attack damage, and take 10% less damage.
A54: Nika | B54: Shimmerstrike | C54: 1000 | D54: Deals damage to the target Legion and inflicts Bruise: HP-30% for 3s. Damage Type: Physical Damage Factor: 1500 | E54: Skill Damage Factor 600/800/1000/1200/1500 HP reduction 10%/15%/20%/25%/30%
A55: Nika | B55: Assassin’s Covenant | D55: All Legions: Increases damage dealt when peacekeeping by 10% and XP gained when peacekeeping by 10%. | E55: Damage dealt during Peacekeeping bonus 3%/4%/5%/6%/8%/10%(Awakened) Hero EXP bonus 3%/4%/5%/6%/8%/10%(Awakened) | G55: TRUE
A56: Nika | B56: Night Prowler | D56: Legion Infantry gain 20% Physical ATK and 10% March Speed. | E56: Infantry unit Physical ATK bonus 10%/12%/14%/16%/20% Infantry unit March Speed bonus 4%/5%/6%/8%/10%
A57: Nika | B57: Blade Maelstrom | D57: Increases Hero Skill damage dealt by Nika’s Legion by 10%, and counterattack damage by 20%. | E57: Hero Skill damage dealt bonus 4%/5%/6%/8%/10% Counterattack damage bonus 10%/12%/14%/16%/20%
A58: Nika | B58: Total Slaughter | D58: When Nika's launches a normal attack, they have a 50% chance to deal damage if the target has fewer than 50% units remaining. Damage Type: Physical Damage Factor: 500 This effect can be triggered once every 2s.
A59: Garwood | B59: Revitalizing Rune | C59: 1000 | D59: Heals lightly wounded units in Garwood's Legion (Healing Factor 1200) and grants them Resistance reducing all damage taken by 20% for 4s. | E59: Healing Factor 500/650/800/1000/1200 Damage taken reduction 10%/12%/14%/16%/20%
A60: Garwood | B60: Tempered Bark | D60: The Legion gains 10% HP. | E60: HP bonus 2%/4%/6%/8%/10%
A61: Garwood | B61: Call of the Ancient Tree | D61: Increases the DEF of all Infantry units in this Legion by 20%, and all healing they grant or receive by 30%. | E61: DEF bonus 10%/12%/14%/16%/20% Healing received bonus 10%/15%/20%/25%/30%
A62: Garwood | B62: Thistles and Thorns | D62: Has a 75% chance to increase Physical damage dealt by 30% for 5s when healed. | E62: Physical Damage Dealt bonus 10%/15%/20%/25%/30%
A63: Garwood | B63: Lifestone | D63: Before Awakening Heals lightly wounded units in Garwood's Legion (Healing Factor 1200) and grants them Resistance reducing all damage taken by 20% for 4s. After Awakening Heals lightly wounded units in Garwood's Legion (Healing Factor 1400) and grants them Resistance reducing all damage taken by 20% for 6s. | F63: Revitalizing Rune
A64: Hosk | B64: No Quarter | C64: 1000 | D64: Hosk’s Legion gains Keen, Vigor, and Rampage, increasing their ATK by 20%, their HP by 30%, and their damage dealt by 10% for 5s. | E64: ATK bonus 10%/12%/14%/16%/20% HP bonus 10%/15%/20%/25%/30% Damage dealt bonus 3%/4%/6%/8%/10%
A65: Hosk | B65: A Dream of Peace | D65: When launching a Rally, Hosk’s normal attacks have a 50% chance to reduce the target’s Physical DEF by 15% for 3s. | E65: DEF reduction 4%/6%/8%/11%/15%
A66: Hosk | B66: Battle-Scarred | D66: Increases a Legion’s DEF by 25% when Hosk is a Commander, and their Normal Attack damage by 40% when Hosk is Deputy. | E66: DEF bonus 10%/13%/16%/20%/25% Normal attack damage bonus 15%/20%/25%/30%/40%
A67: Hosk | B67: Plateau Tactics | D67: Increases maximum Legion Capacity by 15000. | E67: Maximum Legion Capacity bonus 3000/6000/9000/12000/15000
A68: Hosk | B68: Furious Charge | D68: After Hosk’s Legion receives a buff effect, their normal attack Crit Rate is increased by 6% and their counterattack Crit Rate is increased by 6% (up to a maximum of 30%) for 6s.
A69: Emrys | B69: Shattering Blow | C69: 1000 | D69: Deals damage to the target Legion. Damage Type: Physical Damage Factor: 1500 | E69: Skill Damage Factor 700/900/1100/1300/1500
A70: Emrys | B70: Watcher’s Blade | D70: When Emrys’s Legion enters battle, they gain Passion, increasing their Rage Accumulation Speed by 40% for 5s. This effect can be triggered once every 30s. | E70: Rage Accumulation Speed bonus 20%/25%/30%/35%/40%
A71: Emrys | B71: Penumbra | D71: All Cavalry units in Emrys’s Legion gain 30% Physical ATK and 10% March Speed. | E71: Cavalry unit Physical ATK bonus 10%/15%/20%/25%/30% Cavalry unit March Speed bonus 3%/4.5%/6%/8%/10%
A72: Emrys | B72: Shadow Raid | D72: All damage dealt by the Emrys’s Legion is increased by 10%.Emrys's Legion also deals 15% more Skill damage when attacking targets that have been Surrounded. | E72: Damage dealt bonus 4%/5%/6%/8%/10% Hero Skill damage dealt bonus 5%/7%/9%/12%/15%
A73: Emrys | B73: Springblade | D73: When hit a normal attack, Emrys's Legion has a 20% chance to gain Passion, increasing Rage Accumulation Speed by 20% for 5s. If Emrys's Legion already has Passion, it is removed, granting 100 Rage. This effect can be triggered once every 2s.
A74: Madeline | B74: Blessed Blade | C74: 1000 | D74: Grants Physical Keen, increasing Physical ATK by 20% for 4s. Also grants a shield which absorbs damage (Shield Factor 1200) for 4s. | E74: Physical ATK bonus 5%/8%/11%/15%/20% Shield Factor 600/700/800/1000/1200
A75: Madeline | B75: Glorious Bloodline | D75: Increases Legion Capacity by 15000, and increases Physicl damage dealt by Legion in the field by 3%. | E75: Maximum Legion Capacity bonus 3000/6000/9000/12000/15000 Physical Damage Dealt bonus 3%/4%/6%/8%/10%
A76: Madeline | B76: Steel Sentinel | D76: Legion deals 15% more counterattack damage, and all Infantry units in the Legion gain 15% HP. | E76: Infantry unit HP bonus 5%/7%/9%/12%/15% Counterattack damage bonus 5%/7%/9%/12%/15%
A77: Madeline | B77: Piercing Gaze | D77: When Blessed Blade's shield is broken, Madeline deals damage to up to 3 surrounding Legions. Damage Type: Physical Damage Factor: 300 | E77: Skill Damage Factor 100/150/200/250/300
A78: Madeline | B78: The Sword of Sorland | D78: Before Awakening When Blessed Blade's shield is broken, Madeline deals damage to up to 3 surrounding Legions. Damage Type: Physical Damage Factor: 300 After Awakening When Blessed Blade's shield is broken, Madeline deals damage to up to 3 surrounding Legions and gains Resistance: damage taken -10% for 4s.. Damage Type: Physical Damage Factor: 300 | F78: Piercing Gaze
A79: Alwyn | B79: Venomous Overgrowth | C79: 1000 | D79: Deals damage to the target. Damage Type: Magic Damage Factor: 600 Target is also Ensnared for 3s: 1) Deals Magic damage every second (Damage Factor 100) 2) March Speed -10% | E79: Skill Damage Factor 300/360/420/500/600 Continuous Damage Factor 100/100/100/100/100
A80: Alwyn | B80: Wealdshield | D80: Legion Magic units gain 10% Magic ATK and 10% HP. | E80: Magic unit Magic ATK bonus 4%/5%/6%/8%/10% Magic unit HP bonus 4%/5%/6%/8%/10%
A81: Alwyn | B81: Oath of the Wellspring | D81: Legion takes 15% less normal attack damage in the field. | E81: Normal attack damage taken reduction 5%/7%/9%/12%/15%
A82: Alwyn | B82: Friend of the Hemlock | D82: When Legion is hit with a normal attack, 15% chance to Ensnare the attacker for 3s. Ensnared: 1) Deals Magic damage every second (Damage Factor 100) 2) March Speed -10% | E82: Probability 3%/6%/9%/12%/15%
A83: Alwyn | B83: Miasmic Mist | D83: Before Awakening Deals damage to the target. Damage Type: Magic Damage Factor: 600 Target is also Ensnared for 3s: 1) Deals Magic damage every second (Damage Factor 100) 2) March Speed -10% After Awakening Alwyn deals damage to the target Legion and Ensnares them for 3s. If the target is suffering from any other effects that deal Magic damage, Alwyn deals additional damage. Damage Type: Magic Damage Factor: 600 Damage Factor (Additional): 200 Ensnared: 1) Deals Magic damage every second (Damage Factor 100) 2) March Speed -10% | F83: Venomous Overgrowth
A84: Bakhar | B84: Grayclaw Fury | C84: 1000 | D84: Deals damage to the target Legion and grants Bakhar's Legion Rampage: damage dealt by 20% for 4s. Damage Type: Physical Damage Factor: 600 | E84: Skill Damage Factor 300/370/440/510/600 Damage bonus 4%/8%/12%/16%/20%
A85: Bakhar | B85: Boiling Blood | D85: Legion Infantry units Legion gain 10% Physical ATK and 10% DEF. | E85: Infantry unit Physical ATK bonus 3%/4%/6%/8%/10% Infantry unit DEF bonus 3%/4%/6%/8%/10%
A86: Bakhar | B86: Fearsome Roar | D86: When Legion is hit with a normal attack, Legion has a 20% chance to inflict Gloom on the target, reducing their ATK by 25% for 4s. This effect can be triggered once every 10s. | E86: ATK reduction 5%/10%/15%/20%/25%
A87: Bakhar | B87: Tireless Will | D87: Garrisoned Armies takes 15% less Hero Skill damage while garrisoned in a City or Stronghold, and receives 15% more healing. | E87: Hero Skill damage taken reduction 4%/6%/8%/11%/15% Healing granted bonus 4%/6%/8%/11%/15%
A88: Bakhar | B88: Last-Ditch Strike | D88: When Bakhar's Legion has less than 50% units remaining, they have a 50% chance of inflicting Bleed on the target when counterattacking. Bleed: deals damage every second for 3s Damage Type: Physical Damage Factor: 200
A89: Kregg | B89: Fragmentation Bolt | C89: 1000 | D89: Deals damage to the target Legion, and deals additional damage to up to 2 of the nearest Legions. Damage Type: Physical Damage Factor: (Target): 600 Damage Factor (Other Legions): 300 | E89: Skill Damage Factor 200/300/400/500/600 Bomb Additional Damage Factor 100/150/200/250/300
A90: Kregg | B90: Wyvern Rider | D90: Legion deals 10% more Hero Skill damage. After battle ends, they gain 20% March Speed for 10s. | E90: Hero Skill damage dealt bonus 4%/5%/6%/8%/10% March Speed bonus 10%/12%/14%/16%/20%
A91: Kregg | B91: Aerial Formation | D91: Increases Legion’s ATK by 10%. If the Legion is composed entirely of Flying units, units gain 10% DEF. | E91: ATK bonus 4%/5%/6%/8%/10% DEF bonus 4%/5%/6%/8%/10%
A92: Kregg | B92: Building Frenzy | D92: All Legions: Increases Engineering by 22% when building or destroying buildings in the field. | E92: Engineering bonus while building 6%/9%/12%/15%/18%/22%(Awakened) Bonus to Engineering when destroying 6%/9%/12%/15%/18%/22%(Awakened) | G92: TRUE
A93: Kregg | B93: Biggus Bombus | D93: Before Awakening Deals damage to the target Legion, and deals additional damage to up to 2 of the nearest Legions. Damage Type: Physical Damage Factor (Target): 600 Damage Factor (Other Legions): 300 After Awakening Deals damage to the target Legion, and deals additional damage to up to 2 of the nearest Legions. Damage Legions gains Bleed: deals damage every second for 3s. Damage Type: Physical Damage Factor (Target): 800 Damage Factor (Other Legions): 300 Damage Factor (Bleed): 200 | F93: Fragmentation Bolt
A94: Waldyr | B94: Ice Breath | C94: 1000 | D94: Deals damage to the target and 2 nearby Legions and inflicts Gloom: ATK -20% for 2s. Damage Type: Magic Damage Factor: 600 | E94: Skill Damage Factor 300/370/440/510/600 ATK reduction 4%/8%/12%/16%/20%
A95: Waldyr | B95: Royal Court Mage | D95: All Magic units in Waldyr’s Legion gain 10% Magic ATK and 10% HP. | E95: Magic unit Magic ATK bonus 3%/4%/6%/8%/10% Magic unit HP bonus 3%/4%/6%/8%/10%
A96: Waldyr | B96: Frostbite | D96: Waldyr's Legion deals 15% more Hero Skill damage. | E96: Hero Skill damage dealt bonus 4%/6%/8%/11%/15%
A97: Waldyr | B97: Icy Veins | D97: When Waldyr takes Hero Skill damage, his Legion receives a Shield that can absorb a large amount of damage (Shield Factor 600). This effect can be triggered once per 20s. | E97: Shield Factor 200/300/400/500/600
A98: Waldyr | B98: Tide of Winter | D98: Before Awakening Deals damage to the target and 2 nearby Legions and inflicts Gloom: ATK -20% for 2s. Damage Type: Magic Damage Factor: 600 After Awakening Deals damage to the target and 3 nearby Legions and inflicts Gloom and Freeze for 3s. Gloom: ATK -20% Freeze: March Speed -20% Damage Type: Magic Damage Factor: 700 | F98: Ice Breath
A99: Atheus | B99: Smite | C99: 1000 | D99: Deals damage to the target Legion. Damage Type: Magic Damage Factor: 800 | E99: Skill Damage Factor 300/400/500/650/800
A100: Atheus | B100: Eye of Insight | D100: Launching a normal attacks have a 30% chance to grant Atheus’s Legion 60 Rage. | E100: Extra Rage gained 20/30/40/50/60
...

Sheet War Pet Skills
A1: name | B1: attribute | C1: talent | D1: petExclusive | E1: type
A2: Advanced Moonrage | B2: Strength | C2: FALSE | D2: Moonbear | E2: Physical
A3: Advanced Arrogance | B3: Agility | C3: FALSE | D3: Berserk Faedrake | E3: Physical
A4: Advanced Barbarism | B4: Strength | C4: FALSE | D4: Shadow Manticore | E4: Physical
A5: Advanced Chain Strike | B5: Agility | C5: FALSE | E5: Physical
A6: Advanced Concentration | B6: Luck | C6: FALSE | D6: Snowpeak Roc | E6: Physical
A7: Advanced Counterstrike | B7: Agility | C7: FALSE | E7: Physical
A8: Advanced Exuberance | B8: Luck | C8: FALSE | D8: Golden Roc | E8: Physical
A9: Advanced Fierce Attack | B9: Agility | C9: FALSE | E9: Physical
A10: Advanced Follow-Up | B10: Luck | C10: FALSE | E10: Magic
A11: Advanced Friendship | B11: Agility | C11: FALSE | D11: Stripebear | E11: Overall
A12: Advanced Frost Armor | B12: Agility | C12: FALSE | D12: Frostbear | E12: Physical
A13: Advanced Gleaming Blade | B13: Luck | C13: FALSE | D13: Blade Manticore | E13: Physical
A14: Advanced Icecore | B14: Spirit | C14: FALSE | D14: Ice Lizard | E14: Magic
A15: Advanced Infection | B15: Luck | C15: FALSE | D15: Venomous Lizard | E15: Physical
A16: Advanced Painbloom | B16: Spirit | C16: FALSE | D16: Sapphire Faedrake | E16: Magic
A17: Advanced Quickening | B17: Agility | C17: FALSE | D17: Bruinbear | E17: Physical
A18: Advanced Ravage | B18: Luck | C18: FALSE | D18: Night Roc | E18: Physical
A19: Advanced Shadow Hunter | B19: Spirit | C19: FALSE | D19: Shadow Faedrake | E19: Magic
A20: Advanced Soul Source | B20: Intelligence | C20: FALSE | D20: Seraphic Faedrake | E20: Magic
A21: Advanced Stone Aura | B21: Agility | C21: FALSE | D21: Sand Lizard | E21: Overall
A22: Advanced Tempest | B22: Spirit | C22: FALSE | D22: Thunder Lizard | E22: Magic
A23: Advaned Puncture | B23: Luck | C23: FALSE | D23: Barbed Manticore | E23: Physical
A24: Angry Roar | B24: Agility | C24: FALSE | E24: Physical
A25: Arrogance | B25: Agility | C25: FALSE | D25: Berserk Faedrake | E25: Physical
A26: Barbarism | B26: Luck | C26: TRUE | D26: Shadow Manticore | E26: Physical
A27: Blood Roar | B27: Luck | C27: FALSE | E27: Physical
A28: Chain Strike | B28: Agility | C28: FALSE | E28: Physical
A29: Concentration | B29: Luck | C29: TRUE | D29: Snowpeak Roc | E29: Physical
A30: Counterstrike | B30: Endurance | C30: FALSE | E30: Physical
A31: Dauntless | B31: Intelligence | C31: FALSE | E31: Overall
A32: Determined Heart | B32: Endurance | C32: FALSE | E32: Overall
A33: Divine Blessing | B33: Strength | C33: FALSE | E33: Overall
A34: Elemental Harmony | B34: Intelligence | C34: FALSE | E34: Magic
A35: Exuberance | B35: Agility | C35: TRUE | D35: Golden Roc | E35: Physical
A36: Fatal Bite | B36: Strength | C36: FALSE | E36: Physical
A37: Fierce Attack | B37: Strength | C37: FALSE | E37: Physical
A38: Follow-Up | B38: Intelligence | C38: FALSE | E38: Magic
A39: Friendship | B39: Strength | C39: TRUE | D39: Stripebear | E39: Overall
A40: Frost Armor | B40: Strength | C40: TRUE | D40: Frostbear | E40: Physical
A41: Gleaming Blade | B41: Agility | C41: TRUE | D41: Blade Manticore | E41: Physical
A42: Great Care | B42: Intelligence | C42: FALSE | E42: Overall
A43: Heart Wall | B43: Endurance | C43: FALSE | E43: Overall
A44: Icecore | B44: Intelligence | C44: TRUE | D44: Ice Lizard | E44: Magic
A45: Infection | B45: Agility | C45: TRUE | D45: Venomous Lizard | E45: Physical
A46: Intense Arrogance | B46: Luck | C46: FALSE | D46: Berserk Faedrake | E46: Physical
A47: Intense Barbarism | B47: Luck | C47: FALSE | D47: Shadow Manticore | E47: Physical
A48: Intense Chain Strike | B48: Agility | C48: FALSE | E48: Physical
A49: Intense Concentration | B49: Strength | C49: FALSE | D49: Snowpeak Roc | E49: Physical
A50: Intense Counterstrike | B50: Endurance | C50: FALSE | E50: Physical
A51: Intense Exuberance | B51: Luck | C51: FALSE | D51: Golden Roc | E51: Physical
A52: Intense Fierce Attack | B52: Luck | C52: FALSE | E52: Physical
A53: Intense Follow-Up | B53: Luck | C53: FALSE | E53: Magic
A54: Intense Friendship | B54: Endurance | C54: FALSE | D54: Stripebear | E54: Overall
A55: Intense Frost Armor | B55: Endurance | C55: FALSE | D55: Frostbear | E55: Physical
A56: Intense Gleaming Blade | B56: Agility | C56: FALSE | D56: Blade Manticore | E56: Physical
A57: Intense Icecore | B57: Intelligence | C57: FALSE | D57: Ice Lizard | E57: Magic
A58: Intense Infection | B58: Strength | C58: FALSE | D58: Venomous Lizard | E58: Physical
A59: Intense Moonrage | B59: Endurance | C59: FALSE | D59: Moonbear | E59: Physical
A60: Intense Painbloom | B60: Intelligence | C60: FALSE | D60: Sapphire Faedrake | E60: Magic
A61: Intense Puncture | B61: Strength | C61: FALSE | D61: Barbed Manticore | E61: Physical
A62: Intense Quickening | B62: Endurance | C62: FALSE | D62: Bruinbear | E62: Physical
A63: Intense Ravage | B63: Strength | C63: FALSE | D63: Night Roc | E63: Physical
A64: Intense Shadow Hunter | B64: Intelligence | C64: FALSE | D64: Shadow Faedrake | E64: Magic
A65: Intense Soul Source | B65: Spirit | C65: FALSE | D65: Seraphic Faedrake | E65: Magic
A66: Intense Stone Aura | B66: Spirit | C66: FALSE | D66: Sand Lizard | E66: Overall
A67: Magic Fortune | B67: Luck | C67: FALSE | E67: Magic
A68: Magic Spirits | B68: Spirit | C68: FALSE | E68: Magic
A69: Moonrage | B69: Strength | C69: TRUE | D69: Moonbear | E69: Physical
A70: Outbursts of Rage | B70: Agility | C70: FALSE | E70: Overall
A71: Painbloom | B71: Intelligence | C71: TRUE | D71: Sapphire Faedrake | E71: Magic
A72: Puncture | B72: Luck | C72: TRUE | D72: Barbed Manticore | E72: Physical
A73: Quickening | B73: Strength | C73: TRUE | D73: Bruinbear | E73: Physical
A74: Ravage | B74: Luck | C74: TRUE | D74: Night Roc | E74: Physical
A75: Resonance | B75: Spirit | C75: FALSE | E75: Magic
A76: Shadow Hunter | B76: Intelligence | C76: TRUE | D76: Shadow Faedrake | E76: Magic
A77: Soul Source | B77: Intelligence | C77: TRUE | D77: Seraphic Faedrake | E77: Magic
A78: Stone Aura | B78: Intelligence | C78: TRUE | D78: Sand Lizard | E78: Overall
A79: Tempest | B79: Intelligence | C79: TRUE | D79: Thunder Lizard | E79: Magic
A80: Tooth and Claw | B80: Strength | C80: FALSE | E80: Physical
A81: Tranquility | B81: Spirit | C81: FALSE | E81: Overall

Sheet War Pets
A1: name | B1: type
A2: Berserk Faedrake | B2: Physical
A3: Sapphire Faedrake | B3: Magic
A4: Shadow Faedrake | B4: Magic
A5: Golden Roc | B5: Physical
A6: Snowpeak Roc | B6: Physical
A7: Night Roc | B7: Physical
A8: Frostbear | B8: Physical
A9: Stripebear | B9: Overall
A10: Bruinbear | B10: Physical
A11: Sand Lizard | B11: Overall
A12: Moonbear | B12: Physical
... A19: Barbed Manticore | B19: Physical

Sheet War Pets Skill Infos
A1: name | B1: attribute | C1: talent | D1: petExclusive | E1: type | F1: Cost 1 | G1: Cost 2 | H1: Cost 3 | I1: Cost 4
A2: Advanced Moonrage | B2: Strength | C2: FALSE | D2: Moonbear | E2: Physical | F2: 4 | G2: 4 | H2: 4 | I2: 4
A3: Advanced Arrogance | B3: Agility | C3: FALSE | D3: Berserk Faedrake | E3: Physical | F3: 4 | G3: 4 | H3: 4 | I3: 4
A4: Advanced Barbarism | B4: Strength | C4: FALSE | D4: Shadow Manticore | E4: Physical | F4: 4 | G4: 4 | H4: 4 | I4: 4
A5: Advanced Chain Strike | B5: Agility | C5: FALSE | E5: Physical | F5: 3 | G5: 3 | H5: 3 | I5: 3
A6: Advanced Concentration | B6: Luck | C6: FALSE | D6: Snowpeak Roc | E6: Physical | F6: 4 | G6: 4 | H6: 4 | I6: 4
A7: Advanced Counterstrike | B7: Agility | C7: FALSE | E7: Physical | F7: 3 | G7: 3 | H7: 3 | I7: 3
A8: Advanced Exuberance | B8: Luck | C8: FALSE | D8: Golden Roc | E8: Physical | F8: 4 | G8: 4 | H8: 4 | I8: 4
A9: Advanced Fierce Attack | B9: Agility | C9: FALSE | E9: Physical | F9: 3 | G9: 3 | H9: 3 | I9: 3
A10: Advanced Follow-Up | B10: Luck | C10: FALSE | E10: Magic | F10: 3 | G10: 3 | H10: 3 | I10: 3
A11: Advanced Friendship | B11: Agility | C11: FALSE | D11: Stripebear | E11: Overall | F11: 4 | G11: 4 | H11: 4 | I11: 4
A12: Advanced Frost Armor | B12: Agility | C12: FALSE | D12: Frostbear | E12: Physical | F12: 4 | G12: 4 | H12: 4 | I12: 4
A13: Advanced Gleaming Blade | B13: Luck | C13: FALSE | D13: Blade Manticore | E13: Physical | F13: 4 | G13: 4 | H13: 4 | I13: 4
A14: Advanced Icecore | B14: Spirit | C14: FALSE | D14: Ice Lizard | E14: Magic | F14: 4 | G14: 4 | H14: 4 | I14: 4
A15: Advanced Infection | B15: Luck | C15: FALSE | D15: Venomous Lizard | E15: Physical | F15: 4 | G15: 4 | H15: 4 | I15: 4
A16: Advanced Painbloom | B16: Spirit | C16: FALSE | D16: Sapphire Faedrake | E16: Magic | F16: 4 | G16: 4 | H16: 4 | I16: 4
A17: Advanced Quickening | B17: Agility | C17: FALSE | D17: Bruinbear | E17: Physical | F17: 4 | G17: 4 | H17: 4 | I17: 4
A18: Advanced Ravage | B18: Luck | C18: FALSE | D18: Night Roc | E18: Physical | F18: 4 | G18: 4 | H18: 4 | I18: 4
A19: Advanced Shadow Hunter | B19: Spirit | C19: FALSE | D19: Shadow Faedrake | E19: Magic | F19: 4 | G19: 4 | H19: 4 | I19: 4
A20: Advanced Soul Source | B20: Intelligence | C20: FALSE | D20: Seraphic Faedrake | E20: Magic | F20: 4 | G20: 4 | H20: 4 | I20: 4
A21: Advanced Stone Aura | B21: Agility | C21: FALSE | D21: Sand Lizard | E21: Overall | F21: 4 | G21: 4 | H21: 4 | I21: 4
A22: Advanced Tempest | B22: Spirit | C22: FALSE | D22: Thunder Lizard | E22: Magic | F22: 4 | G22: 4 | H22: 4 | I22: 4
A23: Advaned Puncture | B23: Luck | C23: FALSE | D23: Barbed Manticore | E23: Physical | F23: 4 | G23: 4 | H23: 4 | I23: 4
A24: Angry Roar | B24: Agility | C24: FALSE | E24: Physical | F24: 485 | G24: 3124 | H24: 27300 | I24: =H24*5 -> 136500
A25: Arrogance | B25: Agility | C25: FALSE | D25: Berserk Faedrake | E25: Physical | F25: 0 | G25: 0 | H25: 0 | I25: 0
A26: Barbarism | B26: Luck | C26: TRUE | D26: Shadow Manticore | E26: Physical | F26: 0 | G26: 0 | H26: 0 | I26: 0
A27: Blood Roar | B27: Luck | C27: FALSE | E27: Physical | F27: 648 | G27: 3844 | H27: 27300 | I27: =H27*5 -> 136500
A28: Chain Strike | B28: Agility | C28: FALSE | E28: Physical | F28: 187 | G28: 1411 | H28: 7195 | I28: =H28*5 -> 35975
A29: Concentration | B29: Luck | C29: TRUE | D29: Snowpeak Roc | E29: Physical | F29: 0 | G29: 0 | H29: 0 | I29: 0
A30: Counterstrike | B30: Endurance | C30: FALSE | E30: Physical | F30: 88 | G30: 1051 | H30: 7200 | I30: =H30*5 -> 36000
A31: Dauntless | B31: Intelligence | C31: FALSE | E31: Overall | F31: 60 | G31: 360 | H31: 1800 | I31: =H31*5 -> 9000
A32: Determined Heart | B32: Endurance | C32: FALSE | E32: Overall | F32: 60 | G32: 360 | H32: 1800 | I32: =H32*5 -> 9000
A33: Divine Blessing | B33: Strength | C33: FALSE | E33: Overall | F33: 60 | G33: 373 | H33: 4902 | I33: =H33*5 -> 24510
A34: Elemental Harmony | B34: Intelligence | C34: FALSE | E34: Magic | F34: 240 | G34: 1450 | H34: 14671 | I34: =H34*5 -> 73355
A35: Exuberance | B35: Agility | C35: TRUE | D35: Golden Roc | E35: Physical | F35: 0 | G35: 0 | H35: 0 | I35: 0
A36: Fatal Bite | B36: Strength | C36: FALSE | E36: Physical | F36: 960 | G36: 5357 | H36: 27266 | I36: =H36*5 -> 136330
A37: Fierce Attack | B37: Strength | C37: FALSE | E37: Physical | F37: 126 | G37: 984 | H37: 6466 | I37: =H37*5 -> 32330
A38: Follow-Up | B38: Intelligence | C38: FALSE | E38: Magic | F38: 177 | G38: 1356 | H38: 7200 | I38: =H38*5 -> 36000
A39: Friendship | B39: Strength | C39: TRUE | D39: Stripebear | E39: Overall | F39: 0 | G39: 0 | H39: 0 | I39: 0
A40: Frost Armor | B40: Strength | C40: TRUE | D40: Frostbear | E40: Physical | F40: 0 | G40: 0 | H40: 0 | I40: 0
A41: Gleaming Blade | B41: Agility | C41: TRUE | D41: Blade Manticore | E41: Physical | F41: 0 | G41: 0 | H41: 0 | I41: 0
A42: Great Care | B42: Intelligence | C42: FALSE | E42: Overall | F42: 20 | G42: 120 | H42: 1339 | I42: =H42*5 -> 6695
A43: Heart Wall | B43: Endurance | C43: FALSE | E43: Overall | F43: 20 | G43: 120 | H43: 785 | I43: =H43*5 -> 3925
A44: Icecore | B44: Intelligence | C44: TRUE | D44: Ice Lizard | E44: Magic | F44: 0 | G44: 0 | H44: 0 | I44: 0
A45: Infection | B45: Agility | C45: TRUE | D45: Venomous Lizard | E45: Physical | F45: 0 | G45: 0 | H45: 0 | I45: 0
A46: Intense Arrogance | B46: Luck | C46: FALSE | D46: Berserk Faedrake | E46: Physical | F46: 557 | G46: 3926 | H46: 18412 | I46: =H46*5 -> 92060
A47: Intense Barbarism | B47: Luck | C47: FALSE | D47: Shadow Manticore | E47: Physical | F47: 960 | G47: 5771 | H47: 28000 | I47: =H47*5 -> 140000
A48: Intense Chain Strike | B48: Agility | C48: FALSE | E48: Physical | F48: 96 | G48: 1411 | H48: 7195 | I48: =H48*5 -> 35975
A49: Intense Concentration | B49: Strength | C49: FALSE | D49: Snowpeak Roc | E49: Physical | F49: 625 | G49: 5031 | H49: 17618 | I49: =H49*5 -> 88090
A50: Intense Counterstrike | B50: Endurance | C50: FALSE | E50: Physical | F50: 60 | G50: 360 | H50: 4049 | I50: =H50*5 -> 20245
A51: Intense Exuberance | B51: Luck | C51: FALSE | D51: Golden Roc | E51: Physical | F51: 697 | G51: 4606 | H51: 16665 | I51: =H51*5 -> 83325
A52: Intense Fierce Attack | B52: Luck | C52: FALSE | E52: Physical | F52: 67 | G52: 984 | H52: 6466 | I52: =H52*5 -> 32330
A53: Intense Follow-Up | B53: Luck | C53: FALSE | E53: Magic | F53: 62 | G53: 1356 | H53: 7200 | I53: =H53*5 -> 36000
A54: Intense Friendship | B54: Endurance | C54: FALSE | D54: Stripebear | E54: Overall | F54: 570 | G54: 3044 | H54: 11261 | I54: =H54*5 -> 56305
A55: Intense Frost Armor | B55: Endurance | C55: FALSE | D55: Frostbear | E55: Physical | F55: 555 | G55: 3336 | H55: 12951 | I55: =H55*5 -> 64755
A56: Intense Gleaming Blade | B56: Agility | C56: FALSE | D56: Blade Manticore | E56: Physical | F56: 717 | G56: 5800 | H56: 24009 | I56: =H56*5 -> 120045
A57: Intense Icecore | B57: Intelligence | C57: FALSE | D57: Ice Lizard | E57: Magic | F57: 466 | G57: 2393 | H57: 9384 | I57: =H57*5 -> 46920
A58: Intense Infection | B58: Strength | C58: FALSE | D58: Venomous Lizard | E58: Physical | F58: 755 | G58: 5800 | H58: 28000 | I58: =H58*5 -> 140000
A59: Intense Moonrage | B59: Endurance | C59: FALSE | D59: Moonbear | E59: Physical | F59: 985 | G59: 5683 | H59: 27249 | I59: =H59*5 -> 136245
A60: Intense Painbloom | B60: Intelligence | C60: FALSE | D60: Sapphire Faedrake | E60: Magic | F60: 960 | G60: 5800 | H60: 26618 | I60: =H60*5 -> 133090
A61: Intense Puncture | B61: Strength | C61: FALSE | D61: Barbed Manticore | E61: Physical | F61: 615 | G61: 4823 | H61: 22381 | I61: =H61*5 -> 111905
A62: Intense Quickening | B62: Endurance | C62: FALSE | D62: Bruinbear | E62: Physical | F62: 949 | G62: 5796 | H62: 27181 | I62: =H62*5 -> 135905
A63: Intense Ravage | B63: Strength | C63: FALSE | D63: Night Roc | E63: Physical | F63: 650 | G63: 5246 | H63: 20826 | I63: =H63*5 -> 104130
A64: Intense Shadow Hunter | B64: Intelligence | C64: FALSE | D64: Shadow Faedrake | E64: Magic | F64: 862 | G64: 5741 | H64: 27079 | I64: =H64*5 -> 135395
A65: Intense Soul Source | B65: Spirit | C65: FALSE | D65: Seraphic Faedrake | E65: Magic | F65: 960 | G65: 5713 | H65: 27982 | I65: =H65*5 -> 139910
A66: Intense Stone Aura | B66: Spirit | C66: FALSE | D66: Sand Lizard | E66: Overall | F66: 680 | G66: 4140 | H66: 21957 | I66: =H66*5 -> 109785
A67: Magic Fortune | B67: Luck | C67: FALSE | E67: Magic | F67: 391 | G67: 2317 | H67: 22738 | I67: =H67*5 -> 113690
A68: Magic Spirits | B68: Spirit | C68: FALSE | E68: Magic | F68: 699 | G68: 2971 | H68: 26601 | I68: =H68*5 -> 133005
A69: Moonrage | B69: Strength | C69: TRUE | D69: Moonbear | E69: Physical | F69: 0 | G69: 0 | H69: 0 | I69: 0
A70: Outbursts of Rage | B70: Agility | C70: FALSE | E70: Overall | F70: 20 | G70: 121 | H70: 2182 | I70: =H70*5 -> 10910
A71: Painbloom | B71: Intelligence | C71: TRUE | D71: Sapphire Faedrake | E71: Magic | F71: 0 | G71: 0 | H71: 0 | I71: 0
A72: Puncture | B72: Luck | C72: TRUE | D72: Barbed Manticore | E72: Physical | F72: 0 | G72: 0 | H72: 0 | I72: 0
A73: Quickening | B73: Strength | C73: TRUE | D73: Bruinbear | E73: Physical | F73: 0 | G73: 0 | H73: 0 | I73: 0
A74: Ravage | B74: Luck | C74: TRUE | D74: Night Roc | E74: Physical | F74: 0 | G74: 0 | H74: 0 | I74: 0
A75: Resonance | B75: Spirit | C75: FALSE | E75: Magic | F75: 61 | G75: 695 | H75: 7200 | I75: =H75*5 -> 36000
A76: Shadow Hunter | B76: Intelligence | C76: TRUE | D76: Shadow Faedrake | E76: Magic | F76: 0 | G76: 0 | H76: 0 | I76: 0
A77: Soul Source | B77: Intelligence | C77: TRUE | D77: Seraphic Faedrake | E77: Magic | F77: 0 | G77: 0 | H77: 0 | I77: 0
A78: Stone Aura | B78: Intelligence | C78: TRUE | D78: Sand Lizard | E78: Overall | F78: 0 | G78: 0 | H78: 0 | I78: 0
A79: Tempest | B79: Intelligence | C79: TRUE | D79: Thunder Lizard | E79: Magic | F79: 0 | G79: 0 | H79: 0 | I79: 0
A80: Tooth and Claw | B80: Strength | C80: FALSE | E80: Physical | F80: 67 | G80: 784 | H80: 7200 | I80: =H80*5 -> 36000
A81: Tranquility | B81: Spirit | C81: FALSE | E81: Overall | F81: 61 | G81: 431 | H81: 4957 | I81: =H81*5 -> 24785
A82: Manic Might | B82: 0.3 | C82: 0.5 | D82: 0.8 | E82: 1.3 | F82: 20 | G82: 120 | H82: 20 | I82: =H82*5 -> 100
A83: Hit Weakness | B83: 0.8 | C83: 1.3 | D83: 2.1 | E83: 3.3 | F83: 20 | G83: 120 | H83: 897 | I83: =H83*5 -> 4485
A84: Beast Mark | B84: 0.8 | C84: 1.3 | D84: 2.1 | E84: 3.3 | F84: 20 | G84: 120 | H84: 792 | I84: =H84*5 -> 3960
A85: Swift Revenge | B85: 0.8 | C85: 1.3 | D85: 2.1 | E85: 3.3 | F85: 20 | G85: 120 | H85: 724 | I85: =H85*5 -> 3620
A86: Shieldbreaker | B86: 0.3 | C86: 0.5 | D86: 0.8 | E86: 1.3 | F86: 20 | G86: 120 | H86: 990 | I86: =H86*5 -> 4950
A87: Wild Agility | B87: 0.3 | C87: 0.5 | D87: 0.8 | E87: 1.3 | F87: 20 | G87: 120 | H87: 782 | I87: =H87*5 -> 3910
A88: Poison Gland | B88: 0.3 | C88: 0.5 | D88: 0.8 | E88: 1.3 | F88: 20 | G88: 120 | H88: 1061 | I88: =H88*5 -> 5305
A89: Outbursts of Rage | B89: 7 | C89: 11 | D89: 17 | E89: 27 | F89: 20 | G89: 120 | H89: 2127 | I89: =H89*5 -> 10635
A90: Timely Strike | B90: 0.4 | C90: 0.7 | D90: 1.1 | E90: 1.7 | F90: 20 | G90: 120 | H90: 883 | I90: =H90*5 -> 4415
A91: Blood for Blood | B91: 0.4 | C91: 0.7 | D91: 1.1 | E91: 1.7 | F91: 20 | G91: 120 | H91: 837 | I91: =H91*5 -> 4185
A92: Pursuit Predation | B92: 0.4 | C92: 0.7 | D92: 1.1 | E92: 1.7 | F92: 20 | G92: 120 | H92: 794 | I92: =H92*5 -> 3970
A93: Sudden Epiphany | B93: 0.3 | C93: 0.5 | D93: 0.8 | E93: 1.3 | F93: 20 | G93: 120 | H93: 934 | I93: =H93*5 -> 4670
... A104: Interruption | B104: 0.8 | C104: 1.3 | D104: 2.1 | E104: 3.3 | F104: 20 | G104: 120 | H104: 1800 | I104: =H104*5 -> 9000

Sheet War Pets Skill Infos 2
A1: name | B1: attribute | C1: talent | D1: legionStats | E1: petExclusive | F1: type | G1: Cost 1 | H1: Cost 2 | I1: Cost 3 | J1: Cost 4 | K1: value0 | L1: value1 | M1: value2 | N1: value3
A2: Manic Might | B2: Strength | C2: FALSE | D2: TRUE | F2: Physical | G2: 20 | H2: 120 | I2: 20 | J2: =I2*5 -> 100 | K2: 0.3 | L2: 0.5 | M2: 0.8 | N2: 1.3
A3: Hit Weakness | B3: Strength | C3: FALSE | D3: TRUE | F3: Physical | G3: 20 | H3: 120 | I3: 897 | J3: =I3*5 -> 4485 | K3: 0.8 | L3: 1.3 | M3: 2.1 | N3: 3.3
A4: Beast Mark | B4: Strength | C4: FALSE | D4: TRUE | F4: Physical | G4: 20 | H4: 120 | I4: 792 | J4: =I4*5 -> 3960 | K4: 0.8 | L4: 1.3 | M4: 2.1 | N4: 3.3
A5: Swift Revenge | B5: Strength | C5: FALSE | D5: TRUE | F5: Physical | G5: 20 | H5: 120 | I5: 724 | J5: =I5*5 -> 3620 | K5: 0.8 | L5: 1.3 | M5: 2.1 | N5: 3.3
A6: Timely Strike | B6: Agility | C6: FALSE | D6: TRUE | F6: Physical | G6: 20 | H6: 120 | I6: 883 | J6: =I6*5 -> 4415 | K6: 0.4 | L6: 0.7 | M6: 1.1 | N6: 1.7
A7: Blood for Blood | B7: Agility | C7: FALSE | D7: TRUE | F7: Physical | G7: 20 | H7: 120 | I7: 837 | J7: =I7*5 -> 4185 | K7: 0.4 | L7: 0.7 | M7: 1.1 | N7: 1.7
A8: Pursuit Predation | B8: Agility | C8: FALSE | D8: TRUE | F8: Physical | G8: 20 | H8: 120 | I8: 794 | J8: =I8*5 -> 3970 | K8: 0.4 | L8: 0.7 | M8: 1.1 | N8: 1.7
A9: Eviscerate | B9: Luck | C9: FALSE | D9: TRUE | F9: Physical | G9: 20 | H9: 120 | I9: 752 | J9: =I9*5 -> 3760 | K9: 0.4 | L9: 0.7 | M9: 1.1 | N9: 1.7
A10: Hit Back | B10: Luck | C10: FALSE | D10: TRUE | F10: Physical | G10: 20 | H10: 121 | I10: 715 | J10: =I10*5 -> 3575 | K10: 0.4 | L10: 0.7 | M10: 1.1 | N10: 1.7
A11: Track and Hunt | B11: Luck | C11: FALSE | D11: TRUE | F11: Physical | G11: 20 | H11: 120 | I11: 775 | J11: =I11*5 -> 3875 | K11: 0.4 | L11: 0.7 | M11: 1.1 | N11: 1.7
A12: Sudden Epiphany | B12: Intelligence | C12: FALSE | D12: TRUE | F12: Magic | G12: 20 | H12: 120 | I12: 934 | J12: =I12*5 -> 4670 | K12: 0.3 | L12: 0.5 | M12: 0.8 | N12: 1.3
A13: Magic Pulse | B13: Intelligence | C13: FALSE | D13: TRUE | F13: Magic | G13: 20 | H13: 120 | I13: 828 | J13: =I13*5 -> 4140 | K13: 0.8 | L13: 1.3 | M13: 2.1 | N13: 3.3
... A24: Interruption | B24: Luck | C24: FALSE | D24: TRUE | F24: Overall | G24: 20 | H24: 120 | I24: 1800 | J24: =I24*5 -> 9000 | K24: 0.8 | L24: 1.3 | M24: 2.1 | N24: 3.3

Sheet SoS 1 Timeline
A1: Name | B1: Duration | C1: Behemots | D1: Seasonnal Feature | E1: Pass | F1: Merits Store | G1: Statue
A2: Golden Dreams | B2: 0 | C2: Giant Bear | D2: 1st Monolith Slot
A3: End of Indecision | B3: 1.5 | C3: Miasma Giant
A4: Secrets of Decay | B4: 1.5 | E4: 1 | F4: Basic
A5: Star of Hope | B5: 2
A6: The Time Is Now | B6: 1 | C6: Thunder Roc | D6: 2nd Monolith Slot
A7: Great Deeds | B7: 2 | E7: 2
A8: Chest of Desire | B8: 2
A9: Silent Celebration | B9: 1 | C9: Hydra | D9: 3rd Monolith Slot
A10: Conspiracy | B10: 2 | E10: 3 | F10: Standard
A11: War and Peace | B11: 2 | D11: 4th Monolith Slot | G11: Supreme
A12: Ember of Hope | B12: 2
A13: Unparalleled Bravery | B13: 1 | C13: Necrogiant | D13: 5th Monolith Slot
A14: Salvation | B14: 2 | E14: 4 | F14: Premium
A15: Motherland's Call | B15: 2
A16: Swords Into Plowshares | B16: 3 | E16: 5
A17: Peaks and Valleys | B17: 2 | C17: Flame Dragon
A18: Garlands of Praise | B18: 3
A19: Hearts Towards Dawn | B19: 1 | C19: Magma Daemon
A20: Unscarred | B20: 2 | E20: 2 Opened
A21: A Worth Claim | B21: 2
A22: New Dawn | B22: 2

Sheet SoS 5 Timeline
A1: name | B1: duration | C1: behemots | D1: seasonnalFeature | E1: pass | F1: meritStore | G1: statue
A2: Golden Dreams | B2: 0 | C2: Giant Bear | F2: Basic | G2: Runic
A3: End of Indecision | B3: 1.5 | C3: Frost Giant | D3: 3 Proficiency Points
A4: Land of Ice and Snow | B4: 1.5 | E4: 1
A5: Star of Hope | B5: 2
A6: The Time Is Now | B6: 1 | C6: Cosmic Roc | D6: 3 Proficiency Points
A7: An Invite From Beyond | B7: 2 | E7: 2
A8: Chest of Desire | B8: 2 | D8: 3 Proficiency Points | F8: Standard | G8: Supreme
A9: Ember of Hope | B9: 2
A10: Silent Celebration | B10: 1 | D10: 3 Proficiency Points | E10: 3
A11: Motherland's Call | B11: 2 | C11: Charybdis | D11: 4th Monolith Slot
A12: Raging Waves | B12: 2 | D12: 4 Proficiency Points
A13: Unparalleled Bravery | B13: 1 | C13: Necrogiant
A14: Salvation | B14: 2 | E14: 4 | F14: Premium
A15: War and Peace | B15: 2
A16: Swords Into Plowshares | B16: 3 | E16: 5
A17: Peaks and Valleys | B17: 2 | C17: Frost Dragon
A18: Winter's King | B18: 4
A19: Hearts Toward Dawn | B19: 1 | C19: Magma Daemon
A20: Unscarred | B20: 5
B23: =sum(B2:B20) -> 37

Sheet SoS 4 Timeline
A1: name | B1: duration | C1: behemots | D1: seasonnalFeature | E1: pass | F1: statue | G1: summary
A2: Golden Dreams | B2: 0 | C2: Giant Bear
A3: End of Indecision | B3: 1.5 | C3: Giant
A4: The Rockface | B4: 1.5 | E4: 1
A5: Chest of Desire | B5: 2 | F5: Runic
A6: War in the Wilderness | B6: 2
A7: The Time Is Now | B7: 1 | E7: 2
A8: Star of Hope | B8: 2 | C8: Hydra
A9: Conspiracy | B9: 2
A10: Silent Celebration | B10: 1 | E10: 3
A11: War and Peace | B11: 2 | C11: Gear-Sentry
A12: Path of the Shura | B12: 2 | F12: Supreme
A13: Ember of Hope | B13: 2 | C13: Necrogiant
A14: Salvation | B14: 2 | E14: 4 | G14: Mid-Season
A15: Peak and Valleys | B15: 2
A16: Swords Into Plowshares | B16: 3
A17: Unparalleled Bravery | B17: 1 | E17: 5
A18: Eternal Watch | B18: 2
A19: Swords Into Plowshare | B19: 1 | C19: Shadow Dragon
A20: Rage of Shadows | B20: 3
A21: Hearts Toward Dawn | B21: 1 | C21: Magma Daemon
A22: Unscarred | B22: 3 | G22: Late-Season

Sheet SoS 2 Timeline
A1: name | B1: duration | C1: behemots | D1: seasonnalFeature | E1: pass | F1: meritStore | G1: statue
A2: Golden Dreams | B2: 0 | C2: Dire Bear | D2: 2 Talent Points
A3: The Beast | B3: 1.5 | C3: Miasma Giant
A4: Secrets of Decay | B4: 1.5 | D4: 3 Talent Points | E4: 1 | F4: Basic
A5: Star of Hope | B5: 2
A6: The Time Is Now | B6: 1 | C6: Thunder Roc
A7: Great Deeds | B7: 2 | D7: 4 Talent Points | E7: 2
A8: Chest of Desire | B8: 1.5 | G8: Runic
A9: War in the Wilderness | B9: 1.5
A10: Silent Celebration | B10: 1 | E10: 3 | F10: Standard
A11: War and Peace | B11: 2 | C11: Hydra
A12: Conspiracy | B12: 2 | E12: 4
A13: Motherland's Call | B13: 1.5 | G13: Supreme
A14: Ember of Hope | B14: 1.5
A15: Unparalleled Bravery | B15: 1 | E15: 5
A16: Peaks and Valleys | B16: 2 | C16: Necrogiant
A17: Salvation | B17: 2 | E17: 6 | F17: Premium
A18: Scaling the Heights | B18: 2
A19: Swords into Plowshares | B19: 1 | E19: 7
A20: Eternal Watch | B20: 2 | C20: Frost Dragon
A21: Winter's King | B21: 3
A22: Hearts Toward Dawn | B22: 1 | C22: Magma Demon
A23: Unscarred | B23: 2 | E23: 5 Opened
A24: New Dawn | B24: 2
B26: =sum(B2:B25) -> 37

Sheet Copie de SoS 6
A1: name | B1: duration | C1: behemots | D1: seasonnalFeature | E1: pass | F1: statue | G1: summary
A2: Golden Dreams | B2: 0 | C2: Dire Bear | D2: 2 Talent Points
A3: The Beast | B3: 2
A4: The Time Is Now | B4: 1 | D4: Artifacts Variants (Control) | E4: 1
A5: Star of Hope | B5: 2 | F5: Runic
A6: War in the Wilderness | B6: 2 | D6: Artifacts Variants (Support) | E6: 2
A7: Chest of Desire | B7: 2 | C7: Miasma Giant
A8: Secrets of Decay | B8: 2 | C8: Cosmic Roc
A9: An Invite From Beyond | B9: 2
A10: Silent Celebration | B10: 1 | D10: Artifacts Variants (Tank) | F10: Supreme
A11: Ember of Hope | B11: 2 | E11: 3
A12: Motherland's Call | B12: 2 | C12: Charybdis
A13: Raging Waves | B13: 2 | D13: Artifacts Variants (Utility) | G13: Mid-Season
A14: Unparalleled Bravery | B14: 1 | C14: Necrogiant
A15: Salvation | B15: 3 | E15: 4
A16: War and Peace | B16: 2 | C16: Flame Dragon
A17: Garlands of Praise | B17: 5
A18: Hearts Toward Dawn | B18: 1 | C18: Flamea
A19: Burning Hearts | B19: 5 | G19: Late-Season
B33: =sum(B2:B32) -> 37

Sheet Cycle Information
A1: Modulo jour ? | B1: Start Date | C1: End Date
A2: A | B2: 45793 | C2: =B2+42 -> 45835
A3: B | B3: 45807 | C3: =B3+42 -> 45849
A4: C | B4: 45821 | C4: =B4+42 -> 45863
A5: D | B5: 45835 | C5: =B5+42 -> 45877
A11: C | B11: 45849 | C11: =B11+42 -> 45891
A12: D | B12: 45863 | C12: =B12+42 -> 45905

Sheet Event Calendar
A1: 45832 | B1: Trial of Light
A2: 45833 | B2: Smash the Shadows (pas sûr)
A3: 45834
A4: 45835
A5: 45836
A6: 45837
A7: 45838
A8: 45839
A9: 45840
A10: 45841
A11: 45842
A12: 45843
A13: 45844
A14: 45845 | B14: SLE (Range) | C14: Celestial Battlegrounds | E14: | The Jacx
A15: 45846 | B15: Wheel Range | C15: Trial of Light | E15: |
A16: 45847 | B16: Alliance Mobilization | C16: ou le 8 | E16: |
A17: 45848 | B17: Crucible of Courage | E17: |
A18: 45849 | B18: Battle Abyss | E18: |
A19: 45850 | B19: Behemot Raids | E19: |
A20: 45851 | E20: | | F20: Crucible
A21: 45852 | B21: Breaking Through | E21: |
A22: 45853 | B22: Roots of War | C22: Forge of Light (Range) | D22: Battle Abyss | E22: |
A23: 45854 | E23: |
A24: 45855 | E24: | | F24: Breaking Through
A25: 45856 | B25: Battle Abyss | E25: |
A26: 45857 | E26: |
A27: 45858 | E27: |
A28: 45859 | E28: |
A29: 45860 | B29: Trial of Light | E29: |
A30: 45861 | E30: |
A31: 45862 | E31: |
A32: 45863 | B32: BACK TO HK | E32: |
A33: 45864 | B33: Behemot Raids | E33: |
A34: 45865 | B34: Crucible of Courage | E34: |
A35: 45866 | B35: Smash the Shadows | E35: |
A36: 45867 | E36: |
A37: 45868 | E37: |
A38: 45869 | E38: |
A39: 45870 | E39: |
A40: 45871 | E40: |
A41: 45872 | E41: |
A42: 45873 | E42: |
A43: 45874 | B43: Alliance Mobilization
A44: 45875
A45: 45876
A46: 45877
A47: 45878
A48: 45879
A49: 45880
A50: 45881
A51: 45882
A52: 45883
A53: 45884
A54: 45885
A55: 45886
... A61: 45892
